{"statuses":[{"created_at":"Sat Sep 17 20:56:54 +0000 2016","id":777249995648999424,"id_str":"777249995648999424","text":"RT @MOFU_terro: (\u0e51\u2180\u11ba\u2180\u0e51)\u2604 #IS #ISIS #ISIL #Deash #IslamicState #\u062f\u0627\u0639\u0634 #\u0627\u0644\u062f\u0648\u0644\u0629_\u0627\u0644\u0625\u0633\u0644\u0627\u0645\u064a\u0629 #\u0627\u0644\u062f\u0648\u0644\u0629 https:\/\/t.co\/2g3Ky7hD9f","truncated":false,"entities":{"hashtags":[{"text":"IS","indices":[25,28]},{"text":"ISIS","indices":[29,34]},{"text":"ISIL","indices":[35,40]},{"text":"Deash","indices":[41,47]},{"text":"IslamicState","indices":[48,61]},{"text":"\u062f\u0627\u0639\u0634","indices":[62,67]},{"text":"\u0627\u0644\u062f\u0648\u0644\u0629_\u0627\u0644\u0625\u0633\u0644\u0627\u0645\u064a\u0629","indices":[68,85]},{"text":"\u0627\u0644\u062f\u0648\u0644\u0629","indices":[86,93]}],"symbols":[],"user_mentions":[{"screen_name":"MOFU_terro","name":"\u30e2\u30d5\u30c6\u30edbot","id":3486272594,"id_str":"3486272594","indices":[3,14]}],"urls":[],"media":[{"id":649135698864271360,"id_str":"649135698864271360","indices":[94,117],"media_url":"http:\/\/pbs.twimg.com\/media\/CQIxepXUcAAaFWU.jpg","media_url_https":"https:\/\/pbs.twimg.com\/media\/CQIxepXUcAAaFWU.jpg","url":"https:\/\/t.co\/2g3Ky7hD9f","display_url":"pic.twitter.com\/2g3Ky7hD9f","expanded_url":"http:\/\/twitter.com\/MOFU_terro\/status\/649135699707367424\/photo\/1","type":"photo","sizes":{"small":{"w":340,"h":251,"resize":"fit"},"large":{"w":481,"h":355,"resize":"fit"},"thumb":{"w":150,"h":150,"resize":"crop"},"medium":{"w":481,"h":355,"resize":"fit"}},"source_status_id":649135699707367424,"source_status_id_str":"649135699707367424","source_user_id":3486272594,"source_user_id_str":"3486272594"}]},"extended_entities":{"media":[{"id":649135698864271360,"id_str":"649135698864271360","indices":[94,117],"media_url":"http:\/\/pbs.twimg.com\/media\/CQIxepXUcAAaFWU.jpg","media_url_https":"https:\/\/pbs.twimg.com\/media\/CQIxepXUcAAaFWU.jpg","url":"https:\/\/t.co\/2g3Ky7hD9f","display_url":"pic.twitter.com\/2g3Ky7hD9f","expanded_url":"http:\/\/twitter.com\/MOFU_terro\/status\/649135699707367424\/photo\/1","type":"photo","sizes":{"small":{"w":340,"h":251,"resize":"fit"},"large":{"w":481,"h":355,"resize":"fit"},"thumb":{"w":150,"h":150,"resize":"crop"},"medium":{"w":481,"h":355,"resize":"fit"}},"source_status_id":649135699707367424,"source_status_id_str":"649135699707367424","source_user_id":3486272594,"source_user_id_str":"3486272594"}]},"metadata":{"result_type":"recent","iso_language_code":"ko"},"source":"\u003ca href=\"http:\/\/www.floodgap.com\/software\/ttytter\/\" rel=\"nofollow\"\u003eTTYtter\u003c\/a\u003e","in_reply_to_status_id":null,"in_reply_to_status_id_str":null,"in_reply_to_user_id":null,"in_reply_to_user_id_str":null,"in_reply_to_screen_name":null,"user":{"id":4236329059,"id_str":"4236329059","name":"\u9b5a\u66fc","screen_name":"Unagi120","location":"","description":"\u3046\u306a\u304e\u306e\u84b2\u713c\u304d\u753b\u50cf\u3092\u3064\u3076\u3084\u304d\u307e\u3059\u3002\u304d\u3063\u3068\u3046\u306a\u304e\u304c\u98df\u3079\u305f\u304f\u306a\u308b\u3067\u3057\u3087\u3046\u3002 #\u3046\u306a\u304e #\u9c3b #\u84b2\u713c\u304d #unagi","url":null,"entities":{"description":{"urls":[]}},"protected":false,"followers_count":649,"friends_count":773,"listed_count":22,"created_at":"Sat Nov 14 16:25:29 +0000 2015","favourites_count":683,"utc_offset":null,"time_zone":null,"geo_enabled":false,"verified":false,"statuses_count":20466,"lang":"ja","contributors_enabled":false,"is_translator":false,"is_translation_enabled":false,"profile_background_color":"000000","profile_background_image_url":"http:\/\/abs.twimg.com\/images\/themes\/theme1\/bg.png","profile_background_image_url_https":"https:\/\/abs.twimg.com\/images\/themes\/theme1\/bg.png","profile_background_tile":false,"profile_image_url":"http:\/\/pbs.twimg.com\/profile_images\/665581708188610560\/qgxfEFDV_normal.jpg","profile_image_url_https":"https:\/\/pbs.twimg.com\/profile_images\/665581708188610560\/qgxfEFDV_normal.jpg","profile_banner_url":"https:\/\/pbs.twimg.com\/profile_banners\/4236329059\/1447522001","profile_link_color":"ABB8C2","profile_sidebar_border_color":"000000","profile_sidebar_fill_color":"000000","profile_text_color":"000000","profile_use_background_image":false,"has_extended_profile":false,"default_profile":false,"default_profile_image":false,"following":false,"follow_request_sent":false,"notifications":false},"geo":null,"coordinates":null,"place":null,"contributors":null,"retweeted_status":{"created_at":"Sat Sep 17 19:28:04 +0000 2016","id":777227642521001984,"id_str":"777227642521001984","text":"(\u0e51\u2180\u11ba\u2180\u0e51)\u2604 #IS #ISIS #ISIL #Deash #IslamicState #\u062f\u0627\u0639\u0634 #\u0627\u0644\u062f\u0648\u0644\u0629_\u0627\u0644\u0625\u0633\u0644\u0627\u0645\u064a\u0629 #\u0627\u0644\u062f\u0648\u0644\u0629 https:\/\/t.co\/2g3Ky7hD9f","truncated":false,"entities":{"hashtags":[{"text":"IS","indices":[9,12]},{"text":"ISIS","indices":[13,18]},{"text":"ISIL","indices":[19,24]},{"text":"Deash","indices":[25,31]},{"text":"IslamicState","indices":[32,45]},{"text":"\u062f\u0627\u0639\u0634","indices":[46,51]},{"text":"\u0627\u0644\u062f\u0648\u0644\u0629_\u0627\u0644\u0625\u0633\u0644\u0627\u0645\u064a\u0629","indices":[52,69]},{"text":"\u0627\u0644\u062f\u0648\u0644\u0629","indices":[70,77]}],"symbols":[],"user_mentions":[],"urls":[],"media":[{"id":649135698864271360,"id_str":"649135698864271360","indices":[78,101],"media_url":"http:\/\/pbs.twimg.com\/media\/CQIxepXUcAAaFWU.jpg","media_url_https":"https:\/\/pbs.twimg.com\/media\/CQIxepXUcAAaFWU.jpg","url":"https:\/\/t.co\/2g3Ky7hD9f","display_url":"pic.twitter.com\/2g3Ky7hD9f","expanded_url":"http:\/\/twitter.com\/MOFU_terro\/status\/649135699707367424\/photo\/1","type":"photo","sizes":{"small":{"w":340,"h":251,"resize":"fit"},"large":{"w":481,"h":355,"resize":"fit"},"thumb":{"w":150,"h":150,"resize":"crop"},"medium":{"w":481,"h":355,"resize":"fit"}},"source_status_id":649135699707367424,"source_status_id_str":"649135699707367424","source_user_id":3486272594,"source_user_id_str":"3486272594"}]},"extended_entities":{"media":[{"id":649135698864271360,"id_str":"649135698864271360","indices":[78,101],"media_url":"http:\/\/pbs.twimg.com\/media\/CQIxepXUcAAaFWU.jpg","media_url_https":"https:\/\/pbs.twimg.com\/media\/CQIxepXUcAAaFWU.jpg","url":"https:\/\/t.co\/2g3Ky7hD9f","display_url":"pic.twitter.com\/2g3Ky7hD9f","expanded_url":"http:\/\/twitter.com\/MOFU_terro\/status\/649135699707367424\/photo\/1","type":"photo","sizes":{"small":{"w":340,"h":251,"resize":"fit"},"large":{"w":481,"h":355,"resize":"fit"},"thumb":{"w":150,"h":150,"resize":"crop"},"medium":{"w":481,"h":355,"resize":"fit"}},"source_status_id":649135699707367424,"source_status_id_str":"649135699707367424","source_user_id":3486272594,"source_user_id_str":"3486272594"}]},"metadata":{"result_type":"recent","iso_language_code":"ko"},"source":"\u003ca href=\"http:\/\/rakubots.kissa.jp\/\" rel=\"nofollow\"\u003erakubo2\u003c\/a\u003e","in_reply_to_status_id":null,"in_reply_to_status_id_str":null,"in_reply_to_user_id":null,"in_reply_to_user_id_str":null,"in_reply_to_screen_name":null,"user":{"id":3486272594,"id_str":"3486272594","name":"\u30e2\u30d5\u30c6\u30edbot","screen_name":"MOFU_terro","location":"\u306d\u3053\u5927\u597d\u304d","description":"\u6211\u3005\u306e\u7a76\u6975\u7684\u306a\u76ee\u6a19\u306f\u7121\u6148\u60b2\u306a\u30e2\u30d5\u30e2\u30d5\u6c5a\u67d3\u3067\u3042\u308b #ISIS\u3061\u3083\u3093 #ISISchan #ISIS_chan #\u732b #\u732b\u753b\u50cf","url":null,"entities":{"description":{"urls":[]}},"protected":false,"followers_count":534,"friends_count":529,"listed_count":9,"created_at":"Mon Sep 07 22:15:33 +0000 2015","favourites_count":225,"utc_offset":-25200,"time_zone":"Pacific Time (US & Canada)","geo_enabled":false,"verified":false,"statuses_count":5701,"lang":"ja","contributors_enabled":false,"is_translator":false,"is_translation_enabled":false,"profile_background_color":"C0DEED","profile_background_image_url":"http:\/\/abs.twimg.com\/images\/themes\/theme1\/bg.png","profile_background_image_url_https":"https:\/\/abs.twimg.com\/images\/themes\/theme1\/bg.png","profile_background_tile":false,"profile_image_url":"http:\/\/pbs.twimg.com\/profile_images\/641012457910091776\/SK4aML6w_normal.jpg","profile_image_url_https":"https:\/\/pbs.twimg.com\/profile_images\/641012457910091776\/SK4aML6w_normal.jpg","profile_banner_url":"https:\/\/pbs.twimg.com\/profile_banners\/3486272594\/1441664533","profile_link_color":"0084B4","profile_sidebar_border_color":"C0DEED","profile_sidebar_fill_color":"DDEEF6","profile_text_color":"333333","profile_use_background_image":true,"has_extended_profile":false,"default_profile":true,"default_profile_image":false,"following":false,"follow_request_sent":false,"notifications":false},"geo":null,"coordinates":null,"place":null,"contributors":null,"is_quote_status":false,"retweet_count":1,"favorite_count":0,"favorited":false,"retweeted":false,"possibly_sensitive":false,"lang":"ko"},"is_quote_status":false,"retweet_count":1,"favorite_count":0,"favorited":false,"retweeted":false,"possibly_sensitive":false,"lang":"ko"},{"created_at":"Sat Sep 17 19:28:04 +0000 2016","id":777227642521001984,"id_str":"777227642521001984","text":"(\u0e51\u2180\u11ba\u2180\u0e51)\u2604 #IS #ISIS #ISIL #Deash #IslamicState #\u062f\u0627\u0639\u0634 #\u0627\u0644\u062f\u0648\u0644\u0629_\u0627\u0644\u0625\u0633\u0644\u0627\u0645\u064a\u0629 #\u0627\u0644\u062f\u0648\u0644\u0629 https:\/\/t.co\/2g3Ky7hD9f","truncated":false,"entities":{"hashtags":[{"text":"IS","indices":[9,12]},{"text":"ISIS","indices":[13,18]},{"text":"ISIL","indices":[19,24]},{"text":"Deash","indices":[25,31]},{"text":"IslamicState","indices":[32,45]},{"text":"\u062f\u0627\u0639\u0634","indices":[46,51]},{"text":"\u0627\u0644\u062f\u0648\u0644\u0629_\u0627\u0644\u0625\u0633\u0644\u0627\u0645\u064a\u0629","indices":[52,69]},{"text":"\u0627\u0644\u062f\u0648\u0644\u0629","indices":[70,77]}],"symbols":[],"user_mentions":[],"urls":[],"media":[{"id":649135698864271360,"id_str":"649135698864271360","indices":[78,101],"media_url":"http:\/\/pbs.twimg.com\/media\/CQIxepXUcAAaFWU.jpg","media_url_https":"https:\/\/pbs.twimg.com\/media\/CQIxepXUcAAaFWU.jpg","url":"https:\/\/t.co\/2g3Ky7hD9f","display_url":"pic.twitter.com\/2g3Ky7hD9f","expanded_url":"http:\/\/twitter.com\/MOFU_terro\/status\/649135699707367424\/photo\/1","type":"photo","sizes":{"small":{"w":340,"h":251,"resize":"fit"},"large":{"w":481,"h":355,"resize":"fit"},"thumb":{"w":150,"h":150,"resize":"crop"},"medium":{"w":481,"h":355,"resize":"fit"}},"source_status_id":649135699707367424,"source_status_id_str":"649135699707367424","source_user_id":3486272594,"source_user_id_str":"3486272594"}]},"extended_entities":{"media":[{"id":649135698864271360,"id_str":"649135698864271360","indices":[78,101],"media_url":"http:\/\/pbs.twimg.com\/media\/CQIxepXUcAAaFWU.jpg","media_url_https":"https:\/\/pbs.twimg.com\/media\/CQIxepXUcAAaFWU.jpg","url":"https:\/\/t.co\/2g3Ky7hD9f","display_url":"pic.twitter.com\/2g3Ky7hD9f","expanded_url":"http:\/\/twitter.com\/MOFU_terro\/status\/649135699707367424\/photo\/1","type":"photo","sizes":{"small":{"w":340,"h":251,"resize":"fit"},"large":{"w":481,"h":355,"resize":"fit"},"thumb":{"w":150,"h":150,"resize":"crop"},"medium":{"w":481,"h":355,"resize":"fit"}},"source_status_id":649135699707367424,"source_status_id_str":"649135699707367424","source_user_id":3486272594,"source_user_id_str":"3486272594"}]},"metadata":{"result_type":"recent","iso_language_code":"ko"},"source":"\u003ca href=\"http:\/\/rakubots.kissa.jp\/\" rel=\"nofollow\"\u003erakubo2\u003c\/a\u003e","in_reply_to_status_id":null,"in_reply_to_status_id_str":null,"in_reply_to_user_id":null,"in_reply_to_user_id_str":null,"in_reply_to_screen_name":null,"user":{"id":3486272594,"id_str":"3486272594","name":"\u30e2\u30d5\u30c6\u30edbot","screen_name":"MOFU_terro","location":"\u306d\u3053\u5927\u597d\u304d","description":"\u6211\u3005\u306e\u7a76\u6975\u7684\u306a\u76ee\u6a19\u306f\u7121\u6148\u60b2\u306a\u30e2\u30d5\u30e2\u30d5\u6c5a\u67d3\u3067\u3042\u308b #ISIS\u3061\u3083\u3093 #ISISchan #ISIS_chan #\u732b #\u732b\u753b\u50cf","url":null,"entities":{"description":{"urls":[]}},"protected":false,"followers_count":534,"friends_count":529,"listed_count":9,"created_at":"Mon Sep 07 22:15:33 +0000 2015","favourites_count":225,"utc_offset":-25200,"time_zone":"Pacific Time (US & Canada)","geo_enabled":false,"verified":false,"statuses_count":5701,"lang":"ja","contributors_enabled":false,"is_translator":false,"is_translation_enabled":false,"profile_background_color":"C0DEED","profile_background_image_url":"http:\/\/abs.twimg.com\/images\/themes\/theme1\/bg.png","profile_background_image_url_https":"https:\/\/abs.twimg.com\/images\/themes\/theme1\/bg.png","profile_background_tile":false,"profile_image_url":"http:\/\/pbs.twimg.com\/profile_images\/641012457910091776\/SK4aML6w_normal.jpg","profile_image_url_https":"https:\/\/pbs.twimg.com\/profile_images\/641012457910091776\/SK4aML6w_normal.jpg","profile_banner_url":"https:\/\/pbs.twimg.com\/profile_banners\/3486272594\/1441664533","profile_link_color":"0084B4","profile_sidebar_border_color":"C0DEED","profile_sidebar_fill_color":"DDEEF6","profile_text_color":"333333","profile_use_background_image":true,"has_extended_profile":false,"default_profile":true,"default_profile_image":false,"following":false,"follow_request_sent":false,"notifications":false},"geo":null,"coordinates":null,"place":null,"contributors":null,"is_quote_status":false,"retweet_count":1,"favorite_count":0,"favorited":false,"retweeted":false,"possibly_sensitive":false,"lang":"ko"},{"created_at":"Fri Sep 16 17:21:32 +0000 2016","id":776833410404712449,"id_str":"776833410404712449","text":"\uc778\ub958\uc560\uc758 \ubc18\uaca9 #Trump #\ud2b8\ub7fc\ud504 - \uc804 \uc138\uacc4 \uc2dc\ubbfc\uc774 @realDonaldTrump \ub3c4\ub110\ub4dc \ud2b8\ub7fc\ud504\uc5d0\uac8c \ubcf4\ub0b4\ub294 \uacf5\uac1c\uc11c\ud55c\uc5d0 \uc11c\uba85\ud558\uace0 \uc788\uc2b5\ub2c8\ub2e4. #WorldToTrump https:\/\/t.co\/Bi5zgu7tHZ\n\uc11c\uba85\uc880....\uc774\uc0c81\ub07c\uc878\ub77c\ubcd1\uc2e0\uc784...","truncated":false,"entities":{"hashtags":[{"text":"Trump","indices":[8,14]},{"text":"\ud2b8\ub7fc\ud504","indices":[15,19]},{"text":"WorldToTrump","indices":[79,92]}],"symbols":[],"user_mentions":[{"screen_name":"realDonaldTrump","name":"Donald J. Trump","id":25073877,"id_str":"25073877","indices":[31,47]}],"urls":[{"url":"https:\/\/t.co\/Bi5zgu7tHZ","expanded_url":"https:\/\/secure.avaaz.org\/kr\/deartrump\/?wKlWglb","display_url":"secure.avaaz.org\/kr\/deartrump\/?\u2026","indices":[93,116]}]},"metadata":{"result_type":"recent","iso_language_code":"ko"},"source":"\u003ca href=\"http:\/\/twitter.com\/download\/android\" rel=\"nofollow\"\u003eTwitter for Android\u003c\/a\u003e","in_reply_to_status_id":null,"in_reply_to_status_id_str":null,"in_reply_to_user_id":null,"in_reply_to_user_id_str":null,"in_reply_to_screen_name":null,"user":{"id":3904614320,"id_str":"3904614320","name":"[\ud734\ud2b8]\ube44\ud0c0\ubbfc\ub3d9\ud601(\ub79c\ub364\ud655\ub960\ub85c\ub4f1\uc7a5)","screen_name":"lovedhyuck_nct","location":"\ub3d9\ud601\uc774\uc30d\ucee4\ud480\ub77c\uc778\uc758606\ubc88\uc9f8\uc8fc\ub984\uc0ac\uc774\uc758\uc138\ud3ec","description":"\ud574\ucc2c\ub9d8\uc785\ub2c8\ub2e4~^^\/\ud558\uc9c0\ub9cc\uace03\uc774\uc8e0\/\uc798\uc548\uc640\uc694\/\ubc30\ucc99\uc800\uc5bc\ub300\uc544\ub2d9\ub2c8\ub2e4\uc5d4\uc2f5\ud788\ub2e4\uc88b\uc544\uc694\ud83d\ude06\/\ubc30\ucc99\ubcf4\uc774\uba74\ubc14\ub85c\ucc28\ub2e8\ud569\ub2c8\ub2e4\ubc30\ucc99\uc811\uadfc\ub178\ub178\ud574\uc694\/\uc218\ub2a5\ub300\ubc15!!\u2661","url":null,"entities":{"description":{"urls":[]}},"protected":false,"followers_count":69,"friends_count":183,"listed_count":2,"created_at":"Thu Oct 15 16:42:38 +0000 2015","favourites_count":298,"utc_offset":null,"time_zone":null,"geo_enabled":false,"verified":false,"statuses_count":2679,"lang":"ko","contributors_enabled":false,"is_translator":false,"is_translation_enabled":false,"profile_background_color":"C0DEED","profile_background_image_url":"http:\/\/abs.twimg.com\/images\/themes\/theme1\/bg.png","profile_background_image_url_https":"https:\/\/abs.twimg.com\/images\/themes\/theme1\/bg.png","profile_background_tile":false,"profile_image_url":"http:\/\/pbs.twimg.com\/profile_images\/751431963668455424\/CqL119Hj_normal.jpg","profile_image_url_https":"https:\/\/pbs.twimg.com\/profile_images\/751431963668455424\/CqL119Hj_normal.jpg","profile_banner_url":"https:\/\/pbs.twimg.com\/profile_banners\/3904614320\/1467990314","profile_link_color":"0084B4","profile_sidebar_border_color":"C0DEED","profile_sidebar_fill_color":"DDEEF6","profile_text_color":"333333","profile_use_background_image":true,"has_extended_profile":true,"default_profile":true,"default_profile_image":false,"following":false,"follow_request_sent":false,"notifications":false},"geo":null,"coordinates":null,"place":null,"contributors":null,"is_quote_status":false,"retweet_count":0,"favorite_count":0,"favorited":false,"retweeted":false,"possibly_sensitive":false,"lang":"ko"},{"created_at":"Fri Sep 16 00:30:24 +0000 2016","id":776578950801809408,"id_str":"776578950801809408","text":"\ud074\ub9b0\ud134 \ud6c4\ubcf4\uc640 \ud2b8\ub7fc\ud504 \ud6c4\ubcf4\uac00 \ucd94\uac00 \uc758\ub8cc\uae30\ub85d\uc744 \uacf5\uac1c\ud588\uc9c0\ub9cc \uacf5\uac1c\ub41c \uc758\ub8cc\uae30\ub85d\uc774 \ucda9\ubd84\ud558\uc9c0 \uc54a\ub2e4\ub294 \uc9c0\uc801\uc785\ub2c8\ub2e4 https:\/\/t.co\/2NZltbDAy3 #Trump #Clinton #Medical https:\/\/t.co\/l6jKJ96FBX","truncated":false,"entities":{"hashtags":[{"text":"Trump","indices":[80,86]},{"text":"Clinton","indices":[87,95]},{"text":"Medical","indices":[96,104]}],"symbols":[],"user_mentions":[],"urls":[{"url":"https:\/\/t.co\/2NZltbDAy3","expanded_url":"http:\/\/bit.ly\/2cyWjha","display_url":"bit.ly\/2cyWjha","indices":[56,79]}],"media":[{"id":776578948738187264,"id_str":"776578948738187264","indices":[105,128],"media_url":"http:\/\/pbs.twimg.com\/media\/Csb2cHuWAAACr2b.jpg","media_url_https":"https:\/\/pbs.twimg.com\/media\/Csb2cHuWAAACr2b.jpg","url":"https:\/\/t.co\/l6jKJ96FBX","display_url":"pic.twitter.com\/l6jKJ96FBX","expanded_url":"https:\/\/twitter.com\/LA18PrimeNews\/status\/776578950801809408\/photo\/1","type":"photo","sizes":{"medium":{"w":480,"h":360,"resize":"fit"},"thumb":{"w":150,"h":150,"resize":"crop"},"large":{"w":480,"h":360,"resize":"fit"},"small":{"w":480,"h":360,"resize":"fit"}}}]},"extended_entities":{"media":[{"id":776578948738187264,"id_str":"776578948738187264","indices":[105,128],"media_url":"http:\/\/pbs.twimg.com\/media\/Csb2cHuWAAACr2b.jpg","media_url_https":"https:\/\/pbs.twimg.com\/media\/Csb2cHuWAAACr2b.jpg","url":"https:\/\/t.co\/l6jKJ96FBX","display_url":"pic.twitter.com\/l6jKJ96FBX","expanded_url":"https:\/\/twitter.com\/LA18PrimeNews\/status\/776578950801809408\/photo\/1","type":"photo","sizes":{"medium":{"w":480,"h":360,"resize":"fit"},"thumb":{"w":150,"h":150,"resize":"crop"},"large":{"w":480,"h":360,"resize":"fit"},"small":{"w":480,"h":360,"resize":"fit"}}}]},"metadata":{"result_type":"recent","iso_language_code":"ko"},"source":"\u003ca href=\"http:\/\/www.hootsuite.com\" rel=\"nofollow\"\u003eHootsuite\u003c\/a\u003e","in_reply_to_status_id":null,"in_reply_to_status_id_str":null,"in_reply_to_user_id":null,"in_reply_to_user_id_str":null,"in_reply_to_screen_name":null,"user":{"id":321120296,"id_str":"321120296","name":"LA18 \ud504\ub77c\uc784\ub274\uc2a4","screen_name":"LA18PrimeNews","location":"Los Angeles, CA","description":"\uc80a\uc740 \ubc29\uc1a1, \uc0dd\ub3d9\uac10\uc788\ub294 \ub274\uc2a4! LA18 \ud504\ub77c\uc784\ub274\uc2a4!\r\n\ubc29\uc1a1\uc2dc\uac04 \r\n\ubcf8\ubc29: \uc6d4-\uae08 \uc800\ub141 8\uc2dc CH 18.1\r\n\uc7ac\ubc29: \uc6d4-\uae08 \ubc24 10\uc2dc CH 18.9","url":"https:\/\/t.co\/axFkECo47W","entities":{"url":{"urls":[{"url":"https:\/\/t.co\/axFkECo47W","expanded_url":"http:\/\/www.la18.tv","display_url":"la18.tv","indices":[0,23]}]},"description":{"urls":[]}},"protected":false,"followers_count":258,"friends_count":191,"listed_count":58,"created_at":"Tue Jun 21 02:00:15 +0000 2011","favourites_count":61,"utc_offset":-25200,"time_zone":"Pacific Time (US & Canada)","geo_enabled":true,"verified":false,"statuses_count":3610,"lang":"en","contributors_enabled":false,"is_translator":false,"is_translation_enabled":false,"profile_background_color":"0F6E9E","profile_background_image_url":"http:\/\/abs.twimg.com\/images\/themes\/theme1\/bg.png","profile_background_image_url_https":"https:\/\/abs.twimg.com\/images\/themes\/theme1\/bg.png","profile_background_tile":false,"profile_image_url":"http:\/\/pbs.twimg.com\/profile_images\/378800000647766232\/b2159ffc1f58a258dc3b70ebefb6d8a3_normal.jpeg","profile_image_url_https":"https:\/\/pbs.twimg.com\/profile_images\/378800000647766232\/b2159ffc1f58a258dc3b70ebefb6d8a3_normal.jpeg","profile_banner_url":"https:\/\/pbs.twimg.com\/profile_banners\/321120296\/1447117325","profile_link_color":"1B95E0","profile_sidebar_border_color":"C0DEED","profile_sidebar_fill_color":"DDEEF6","profile_text_color":"333333","profile_use_background_image":true,"has_extended_profile":false,"default_profile":false,"default_profile_image":false,"following":false,"follow_request_sent":false,"notifications":false},"geo":null,"coordinates":null,"place":null,"contributors":null,"is_quote_status":false,"retweet_count":0,"favorite_count":0,"favorited":false,"retweeted":false,"possibly_sensitive":false,"lang":"ko"},{"created_at":"Thu Sep 15 02:56:56 +0000 2016","id":776253437092560896,"id_str":"776253437092560896","text":"\uc7ac\ub2e8\uacfc \uac1c\uc778\uc740 \ubcc4\uac1c\uc758 \uc778\uaca9\uccb4\n\n#Trump bought a 6-foot-tall portrait of himself with charity money.  https:\/\/t.co\/uEVnQiXbSP :@washingtonpost","truncated":false,"entities":{"hashtags":[{"text":"Trump","indices":[17,23]}],"symbols":[],"user_mentions":[{"screen_name":"washingtonpost","name":"Washington Post","id":2467791,"id_str":"2467791","indices":[111,126]}],"urls":[{"url":"https:\/\/t.co\/uEVnQiXbSP","expanded_url":"http:\/\/wapo.st\/2cy9uAs","display_url":"wapo.st\/2cy9uAs","indices":[86,109]}]},"metadata":{"result_type":"recent","iso_language_code":"ko"},"source":"\u003ca href=\"http:\/\/twitter.com\" rel=\"nofollow\"\u003eTwitter Web Client\u003c\/a\u003e","in_reply_to_status_id":null,"in_reply_to_status_id_str":null,"in_reply_to_user_id":null,"in_reply_to_user_id_str":null,"in_reply_to_screen_name":null,"user":{"id":48626147,"id_str":"48626147","name":"qlstnfp","screen_name":"qlstnfp","location":"\uc11c\uc6b8 ","description":"\uadf8\ub0e5 \uc8fc\uc800\ub9ac \uc8fc\uc800\ub9ac \ud5db\uc18c\ub9ac...\ubcbd\ubcf4\uace0 \uc9c0\uaec4\ub9ac\ub294 \uac70 \uadf8\ub0e5 \uadf8\ub7ec\ub7ec\ub2c8 \ubcf4\uc544\uc8fc\uc138\uc694. \n\n\uadf8\ub7f0\ub370 \uc138\uc0c1\uc774 \uc880 \uc544\ub2c8 \ub9ce\uc774 \uc774\uc0c1\ud569\ub2c8\ub2e4.","url":null,"entities":{"description":{"urls":[]}},"protected":false,"followers_count":10285,"friends_count":1417,"listed_count":175,"created_at":"Fri Jun 19 05:56:22 +0000 2009","favourites_count":408,"utc_offset":32400,"time_zone":"Seoul","geo_enabled":false,"verified":false,"statuses_count":108965,"lang":"en","contributors_enabled":false,"is_translator":false,"is_translation_enabled":false,"profile_background_color":"14191A","profile_background_image_url":"http:\/\/abs.twimg.com\/images\/themes\/theme6\/bg.gif","profile_background_image_url_https":"https:\/\/abs.twimg.com\/images\/themes\/theme6\/bg.gif","profile_background_tile":false,"profile_image_url":"http:\/\/pbs.twimg.com\/profile_images\/475575061126979584\/2uMCo_3D_normal.jpeg","profile_image_url_https":"https:\/\/pbs.twimg.com\/profile_images\/475575061126979584\/2uMCo_3D_normal.jpeg","profile_link_color":"4B58AB","profile_sidebar_border_color":"FFFFFF","profile_sidebar_fill_color":"A0C5C7","profile_text_color":"333333","profile_use_background_image":true,"has_extended_profile":false,"default_profile":false,"default_profile_image":false,"following":false,"follow_request_sent":false,"notifications":false},"geo":null,"coordinates":null,"place":null,"contributors":null,"is_quote_status":false,"retweet_count":0,"favorite_count":0,"favorited":false,"retweeted":false,"possibly_sensitive":false,"lang":"ko"},{"created_at":"Thu Sep 15 00:52:22 +0000 2016","id":776222089439162368,"id_str":"776222089439162368","text":"\ud2b8\ub7fc\ud504\ub3c4 \uacf5\uac1c\n#Clinton, #Trump move to show medical fitness for White House https:\/\/t.co\/f4ZmBAbso1  https:\/\/t.co\/qVFGyyufZj :@Reuters","truncated":false,"entities":{"hashtags":[{"text":"Clinton","indices":[8,16]},{"text":"Trump","indices":[18,24]}],"symbols":[],"user_mentions":[{"screen_name":"Reuters","name":"Reuters Top News","id":1652541,"id_str":"1652541","indices":[120,128]}],"urls":[{"url":"https:\/\/t.co\/f4ZmBAbso1","expanded_url":"http:\/\/reut.rs\/2cbzJO6","display_url":"reut.rs\/2cbzJO6","indices":[70,93]}],"media":[{"id":776217732148789248,"id_str":"776217732148789248","indices":[95,118],"media_url":"http:\/\/pbs.twimg.com\/media\/CsWt6jEWgAAEyQc.jpg","media_url_https":"https:\/\/pbs.twimg.com\/media\/CsWt6jEWgAAEyQc.jpg","url":"https:\/\/t.co\/qVFGyyufZj","display_url":"pic.twitter.com\/qVFGyyufZj","expanded_url":"https:\/\/twitter.com\/Reuters\/status\/776217733755265025\/photo\/1","type":"photo","sizes":{"large":{"w":816,"h":545,"resize":"fit"},"small":{"w":680,"h":454,"resize":"fit"},"medium":{"w":816,"h":545,"resize":"fit"},"thumb":{"w":150,"h":150,"resize":"crop"}},"source_status_id":776217733755265025,"source_status_id_str":"776217733755265025","source_user_id":1652541,"source_user_id_str":"1652541"}]},"extended_entities":{"media":[{"id":776217732148789248,"id_str":"776217732148789248","indices":[95,118],"media_url":"http:\/\/pbs.twimg.com\/media\/CsWt6jEWgAAEyQc.jpg","media_url_https":"https:\/\/pbs.twimg.com\/media\/CsWt6jEWgAAEyQc.jpg","url":"https:\/\/t.co\/qVFGyyufZj","display_url":"pic.twitter.com\/qVFGyyufZj","expanded_url":"https:\/\/twitter.com\/Reuters\/status\/776217733755265025\/photo\/1","type":"photo","sizes":{"large":{"w":816,"h":545,"resize":"fit"},"small":{"w":680,"h":454,"resize":"fit"},"medium":{"w":816,"h":545,"resize":"fit"},"thumb":{"w":150,"h":150,"resize":"crop"}},"source_status_id":776217733755265025,"source_status_id_str":"776217733755265025","source_user_id":1652541,"source_user_id_str":"1652541"}]},"metadata":{"result_type":"recent","iso_language_code":"ko"},"source":"\u003ca href=\"http:\/\/twitter.com\" rel=\"nofollow\"\u003eTwitter Web Client\u003c\/a\u003e","in_reply_to_status_id":776173829592788992,"in_reply_to_status_id_str":"776173829592788992","in_reply_to_user_id":48626147,"in_reply_to_user_id_str":"48626147","in_reply_to_screen_name":"qlstnfp","user":{"id":48626147,"id_str":"48626147","name":"qlstnfp","screen_name":"qlstnfp","location":"\uc11c\uc6b8 ","description":"\uadf8\ub0e5 \uc8fc\uc800\ub9ac \uc8fc\uc800\ub9ac \ud5db\uc18c\ub9ac...\ubcbd\ubcf4\uace0 \uc9c0\uaec4\ub9ac\ub294 \uac70 \uadf8\ub0e5 \uadf8\ub7ec\ub7ec\ub2c8 \ubcf4\uc544\uc8fc\uc138\uc694. \n\n\uadf8\ub7f0\ub370 \uc138\uc0c1\uc774 \uc880 \uc544\ub2c8 \ub9ce\uc774 \uc774\uc0c1\ud569\ub2c8\ub2e4.","url":null,"entities":{"description":{"urls":[]}},"protected":false,"followers_count":10285,"friends_count":1417,"listed_count":175,"created_at":"Fri Jun 19 05:56:22 +0000 2009","favourites_count":408,"utc_offset":32400,"time_zone":"Seoul","geo_enabled":false,"verified":false,"statuses_count":108965,"lang":"en","contributors_enabled":false,"is_translator":false,"is_translation_enabled":false,"profile_background_color":"14191A","profile_background_image_url":"http:\/\/abs.twimg.com\/images\/themes\/theme6\/bg.gif","profile_background_image_url_https":"https:\/\/abs.twimg.com\/images\/themes\/theme6\/bg.gif","profile_background_tile":false,"profile_image_url":"http:\/\/pbs.twimg.com\/profile_images\/475575061126979584\/2uMCo_3D_normal.jpeg","profile_image_url_https":"https:\/\/pbs.twimg.com\/profile_images\/475575061126979584\/2uMCo_3D_normal.jpeg","profile_link_color":"4B58AB","profile_sidebar_border_color":"FFFFFF","profile_sidebar_fill_color":"A0C5C7","profile_text_color":"333333","profile_use_background_image":true,"has_extended_profile":false,"default_profile":false,"default_profile_image":false,"following":false,"follow_request_sent":false,"notifications":false},"geo":null,"coordinates":null,"place":null,"contributors":null,"is_quote_status":false,"retweet_count":0,"favorite_count":0,"favorited":false,"retweeted":false,"possibly_sensitive":false,"lang":"ko"},{"created_at":"Mon Sep 12 09:52:31 +0000 2016","id":775270860370378752,"id_str":"775270860370378752","text":"#TweetMovie #ux Watch #Isis #Isil unfold at https:\/\/t.co\/70Ul4g8bYO \u007bargentina, \uc0ac\uc124\ud1a0\ud1a0\ucd94\ucc9c\uc0ac\uc774\ud2b8, #islamic, women, fighting, #muslim\u007d","truncated":false,"entities":{"hashtags":[{"text":"TweetMovie","indices":[0,11]},{"text":"ux","indices":[12,15]},{"text":"Isis","indices":[22,27]},{"text":"Isil","indices":[28,33]},{"text":"islamic","indices":[91,99]},{"text":"muslim","indices":[118,125]}],"symbols":[],"user_mentions":[],"urls":[{"url":"https:\/\/t.co\/70Ul4g8bYO","expanded_url":"http:\/\/postmodernnews.com\/token-tv.aspx?f=isis816&e=PMN_Politics&start=31","display_url":"postmodernnews.com\/token-tv.aspx?\u2026","indices":[44,67]}]},"metadata":{"result_type":"recent","iso_language_code":"ko"},"source":"\u003ca href=\"http:\/\/postmodernnews.com\/Default.aspx?startFolder=1\" rel=\"nofollow\"\u003ePMN Politics\u003c\/a\u003e","in_reply_to_status_id":null,"in_reply_to_status_id_str":null,"in_reply_to_user_id":null,"in_reply_to_user_id_str":null,"in_reply_to_screen_name":null,"user":{"id":198238726,"id_str":"198238726","name":"PMN Politics","screen_name":"PMN_Politics","location":"","description":"Political deconstructions from PostModernNews\u2122.  Tweets sent reflect a current slice of Twitter as keywords.","url":"http:\/\/t.co\/diLvG0LgSy","entities":{"url":{"urls":[{"url":"http:\/\/t.co\/diLvG0LgSy","expanded_url":"http:\/\/postmodernnews.com?startFolder=1","display_url":"postmodernnews.com\/?startFolder=1","indices":[0,22]}]},"description":{"urls":[]}},"protected":false,"followers_count":464,"friends_count":31,"listed_count":861,"created_at":"Sun Oct 03 19:01:15 +0000 2010","favourites_count":13058,"utc_offset":null,"time_zone":null,"geo_enabled":false,"verified":false,"statuses_count":47403,"lang":"en","contributors_enabled":false,"is_translator":false,"is_translation_enabled":false,"profile_background_color":"C0DEED","profile_background_image_url":"http:\/\/abs.twimg.com\/images\/themes\/theme1\/bg.png","profile_background_image_url_https":"https:\/\/abs.twimg.com\/images\/themes\/theme1\/bg.png","profile_background_tile":false,"profile_image_url":"http:\/\/pbs.twimg.com\/profile_images\/378800000221190769\/e1d740ebc4ddcb8419c12552af3b66d5_normal.jpeg","profile_image_url_https":"https:\/\/pbs.twimg.com\/profile_images\/378800000221190769\/e1d740ebc4ddcb8419c12552af3b66d5_normal.jpeg","profile_link_color":"0084B4","profile_sidebar_border_color":"C0DEED","profile_sidebar_fill_color":"DDEEF6","profile_text_color":"333333","profile_use_background_image":true,"has_extended_profile":false,"default_profile":true,"default_profile_image":false,"following":false,"follow_request_sent":false,"notifications":false},"geo":null,"coordinates":null,"place":null,"contributors":null,"is_quote_status":false,"retweet_count":0,"favorite_count":0,"favorited":false,"retweeted":false,"possibly_sensitive":false,"lang":"ko"},{"created_at":"Mon Sep 12 00:49:47 +0000 2016","id":775134275771305984,"id_str":"775134275771305984","text":"\ubc14\ube0c\ub9b0\uce74 #usopen CHAMP! \ud83d\ude4c\ud83d\udc4d\ud83d\udc4f\ud83d\udc4f https:\/\/t.co\/zmjKToEv2P","truncated":false,"entities":{"hashtags":[{"text":"usopen","indices":[5,12]}],"symbols":[],"user_mentions":[],"urls":[{"url":"https:\/\/t.co\/zmjKToEv2P","expanded_url":"https:\/\/twitter.com\/usopen\/status\/775130723162333184","display_url":"twitter.com\/usopen\/status\/\u2026","indices":[25,48]}]},"metadata":{"result_type":"recent","iso_language_code":"ko"},"source":"\u003ca href=\"http:\/\/twitter.com\/download\/android\" rel=\"nofollow\"\u003eTwitter for Android\u003c\/a\u003e","in_reply_to_status_id":null,"in_reply_to_status_id_str":null,"in_reply_to_user_id":null,"in_reply_to_user_id_str":null,"in_reply_to_screen_name":null,"user":{"id":42845175,"id_str":"42845175","name":"\uc774\ud615\ubbf8","screen_name":"LeeHyungMi","location":"Seoul, Korea","description":"Thank you","url":"http:\/\/t.co\/P1KddofhMe","entities":{"url":{"urls":[{"url":"http:\/\/t.co\/P1KddofhMe","expanded_url":"http:\/\/leehyungmi.wordpress.com","display_url":"leehyungmi.wordpress.com","indices":[0,22]}]},"description":{"urls":[]}},"protected":false,"followers_count":55,"friends_count":81,"listed_count":2,"created_at":"Wed May 27 08:46:17 +0000 2009","favourites_count":138,"utc_offset":32400,"time_zone":"Seoul","geo_enabled":false,"verified":false,"statuses_count":366,"lang":"ko","contributors_enabled":false,"is_translator":false,"is_translation_enabled":false,"profile_background_color":"EDECE9","profile_background_image_url":"http:\/\/abs.twimg.com\/images\/themes\/theme3\/bg.gif","profile_background_image_url_https":"https:\/\/abs.twimg.com\/images\/themes\/theme3\/bg.gif","profile_background_tile":false,"profile_image_url":"http:\/\/pbs.twimg.com\/profile_images\/1130870862\/_______6_normal.jpg","profile_image_url_https":"https:\/\/pbs.twimg.com\/profile_images\/1130870862\/_______6_normal.jpg","profile_link_color":"088253","profile_sidebar_border_color":"D3D2CF","profile_sidebar_fill_color":"E3E2DE","profile_text_color":"634047","profile_use_background_image":true,"has_extended_profile":false,"default_profile":false,"default_profile_image":false,"following":false,"follow_request_sent":false,"notifications":false},"geo":null,"coordinates":null,"place":null,"contributors":null,"is_quote_status":true,"quoted_status_id":775130723162333184,"quoted_status_id_str":"775130723162333184","quoted_status":{"created_at":"Mon Sep 12 00:35:40 +0000 2016","id":775130723162333184,"id_str":"775130723162333184","text":"\ud83c\udfc6\ud83c\udfc6\ud83c\udfc6\ud83c\udfc6\ud83c\udfc6\ud83c\udfc6 Congratulations, .@stanwawrinka! #usopen https:\/\/t.co\/Ar5JZhIOp2","truncated":false,"entities":{"hashtags":[{"text":"usopen","indices":[40,47]}],"symbols":[],"user_mentions":[{"screen_name":"stanwawrinka","name":"Stanislas Wawrinka","id":65187067,"id_str":"65187067","indices":[25,38]}],"urls":[{"url":"https:\/\/t.co\/Ar5JZhIOp2","expanded_url":"https:\/\/twitter.com\/usopen\/status\/775130723162333184\/photo\/1","display_url":"pic.twitter.com\/Ar5JZhIOp2","indices":[48,71]}]},"metadata":{"result_type":"recent","iso_language_code":"ko"},"source":"\u003ca href=\"http:\/\/snappytv.com\" rel=\"nofollow\"\u003eSnappyTV.com\u003c\/a\u003e","in_reply_to_status_id":null,"in_reply_to_status_id_str":null,"in_reply_to_user_id":null,"in_reply_to_user_id_str":null,"in_reply_to_screen_name":null,"user":{"id":14836197,"id_str":"14836197","name":"US Open Tennis","screen_name":"usopen","location":"Flushing Meadows, New York","description":"Official Twitter of the US Open Tennis Championships | 2016 Dates: 8\/29 - 9\/11 | Terms of Use: https:\/\/t.co\/SXV9s3SLcd | #usopen","url":"http:\/\/t.co\/4Ilr5i7adf","entities":{"url":{"urls":[{"url":"http:\/\/t.co\/4Ilr5i7adf","expanded_url":"http:\/\/www.usopen.org","display_url":"usopen.org","indices":[0,22]}]},"description":{"urls":[{"url":"https:\/\/t.co\/SXV9s3SLcd","expanded_url":"http:\/\/bit.ly\/2bLWjNB","display_url":"bit.ly\/2bLWjNB","indices":[95,118]}]}},"protected":false,"followers_count":1187552,"friends_count":2390,"listed_count":8606,"created_at":"Mon May 19 18:35:03 +0000 2008","favourites_count":13959,"utc_offset":-14400,"time_zone":"Eastern Time (US & Canada)","geo_enabled":true,"verified":true,"statuses_count":21790,"lang":"en","contributors_enabled":false,"is_translator":false,"is_translation_enabled":false,"profile_background_color":"004B85","profile_background_image_url":"http:\/\/pbs.twimg.com\/profile_background_images\/643265509073514496\/q9jGC2Qe.jpg","profile_background_image_url_https":"https:\/\/pbs.twimg.com\/profile_background_images\/643265509073514496\/q9jGC2Qe.jpg","profile_background_tile":false,"profile_image_url":"http:\/\/pbs.twimg.com\/profile_images\/643265101357797376\/oMuUZQHZ_normal.jpg","profile_image_url_https":"https:\/\/pbs.twimg.com\/profile_images\/643265101357797376\/oMuUZQHZ_normal.jpg","profile_banner_url":"https:\/\/pbs.twimg.com\/profile_banners\/14836197\/1473648666","profile_link_color":"0090FF","profile_sidebar_border_color":"FFFFFF","profile_sidebar_fill_color":"252429","profile_text_color":"666666","profile_use_background_image":true,"has_extended_profile":false,"default_profile":false,"default_profile_image":false,"following":false,"follow_request_sent":false,"notifications":false},"geo":null,"coordinates":null,"place":null,"contributors":null,"is_quote_status":false,"retweet_count":1959,"favorite_count":2514,"favorited":false,"retweeted":false,"possibly_sensitive":false,"lang":"en"},"retweet_count":0,"favorite_count":0,"favorited":false,"retweeted":false,"possibly_sensitive":false,"lang":"ko"},{"created_at":"Sun Sep 11 23:12:16 +0000 2016","id":775109734496030720,"id_str":"775109734496030720","text":"\ub274\uc695\ub118\uac00\uace0\uc2f6\ub124 #GoWawrinka #USOpen https:\/\/t.co\/nKzkqWHUrV","truncated":false,"entities":{"hashtags":[{"text":"GoWawrinka","indices":[8,19]},{"text":"USOpen","indices":[20,27]}],"symbols":[],"user_mentions":[],"urls":[],"media":[{"id":775109724597473280,"id_str":"775109724597473280","indices":[28,51],"media_url":"http:\/\/pbs.twimg.com\/media\/CsG-MBSVUAANpGu.jpg","media_url_https":"https:\/\/pbs.twimg.com\/media\/CsG-MBSVUAANpGu.jpg","url":"https:\/\/t.co\/nKzkqWHUrV","display_url":"pic.twitter.com\/nKzkqWHUrV","expanded_url":"https:\/\/twitter.com\/redosier_\/status\/775109734496030720\/photo\/1","type":"photo","sizes":{"medium":{"w":1200,"h":900,"resize":"fit"},"small":{"w":680,"h":510,"resize":"fit"},"thumb":{"w":150,"h":150,"resize":"crop"},"large":{"w":2048,"h":1536,"resize":"fit"}}}]},"extended_entities":{"media":[{"id":775109724597473280,"id_str":"775109724597473280","indices":[28,51],"media_url":"http:\/\/pbs.twimg.com\/media\/CsG-MBSVUAANpGu.jpg","media_url_https":"https:\/\/pbs.twimg.com\/media\/CsG-MBSVUAANpGu.jpg","url":"https:\/\/t.co\/nKzkqWHUrV","display_url":"pic.twitter.com\/nKzkqWHUrV","expanded_url":"https:\/\/twitter.com\/redosier_\/status\/775109734496030720\/photo\/1","type":"photo","sizes":{"medium":{"w":1200,"h":900,"resize":"fit"},"small":{"w":680,"h":510,"resize":"fit"},"thumb":{"w":150,"h":150,"resize":"crop"},"large":{"w":2048,"h":1536,"resize":"fit"}}}]},"metadata":{"result_type":"recent","iso_language_code":"ko"},"source":"\u003ca href=\"http:\/\/twitter.com\/download\/iphone\" rel=\"nofollow\"\u003eTwitter for iPhone\u003c\/a\u003e","in_reply_to_status_id":null,"in_reply_to_status_id_str":null,"in_reply_to_user_id":null,"in_reply_to_user_id_str":null,"in_reply_to_screen_name":null,"user":{"id":4890437953,"id_str":"4890437953","name":"osier","screen_name":"redosier_","location":"","description":"","url":null,"entities":{"description":{"urls":[]}},"protected":false,"followers_count":21,"friends_count":151,"listed_count":1,"created_at":"Thu Feb 11 00:59:36 +0000 2016","favourites_count":161,"utc_offset":-25200,"time_zone":"Pacific Time (US & Canada)","geo_enabled":false,"verified":false,"statuses_count":1148,"lang":"ko","contributors_enabled":false,"is_translator":false,"is_translation_enabled":false,"profile_background_color":"F5F8FA","profile_background_image_url":null,"profile_background_image_url_https":null,"profile_background_tile":false,"profile_image_url":"http:\/\/pbs.twimg.com\/profile_images\/776391723240919041\/gIkNCN3A_normal.jpg","profile_image_url_https":"https:\/\/pbs.twimg.com\/profile_images\/776391723240919041\/gIkNCN3A_normal.jpg","profile_banner_url":"https:\/\/pbs.twimg.com\/profile_banners\/4890437953\/1473941418","profile_link_color":"2B7BB9","profile_sidebar_border_color":"C0DEED","profile_sidebar_fill_color":"DDEEF6","profile_text_color":"333333","profile_use_background_image":true,"has_extended_profile":false,"default_profile":true,"default_profile_image":false,"following":false,"follow_request_sent":false,"notifications":false},"geo":null,"coordinates":null,"place":null,"contributors":null,"is_quote_status":false,"retweet_count":0,"favorite_count":0,"favorited":false,"retweeted":false,"possibly_sensitive":false,"lang":"ko"},{"created_at":"Sun Sep 11 23:09:05 +0000 2016","id":775108935011405825,"id_str":"775108935011405825","text":"\uc2a4\ud0dc \ud640\ub4dc \ud588\ub2e4!!!! LET'S WIN THIS SET!!!!! COME ON STAN!! @stanwawrinka #Stanimal #StanTheMan #USOpen","truncated":false,"entities":{"hashtags":[{"text":"Stanimal","indices":[66,75]},{"text":"StanTheMan","indices":[76,87]},{"text":"USOpen","indices":[88,95]}],"symbols":[],"user_mentions":[{"screen_name":"stanwawrinka","name":"Stanislas Wawrinka","id":65187067,"id_str":"65187067","indices":[52,65]}],"urls":[]},"metadata":{"result_type":"recent","iso_language_code":"ko"},"source":"\u003ca href=\"http:\/\/twitter.com\/download\/android\" rel=\"nofollow\"\u003eTwitter for Android\u003c\/a\u003e","in_reply_to_status_id":null,"in_reply_to_status_id_str":null,"in_reply_to_user_id":null,"in_reply_to_user_id_str":null,"in_reply_to_screen_name":null,"user":{"id":2593332564,"id_str":"2593332564","name":"doles","screen_name":"doleshka","location":"","description":"ALO14 \/ JL99 \/ Chelsea FC \/ Rory McIlroy \/ Stanimal & Delpo \/ Packers & Aaron Rodgers","url":null,"entities":{"description":{"urls":[]}},"protected":false,"followers_count":253,"friends_count":405,"listed_count":52,"created_at":"Sat Jun 28 16:31:53 +0000 2014","favourites_count":249,"utc_offset":-10800,"time_zone":"Atlantic Time (Canada)","geo_enabled":false,"verified":false,"statuses_count":16599,"lang":"en","contributors_enabled":false,"is_translator":false,"is_translation_enabled":false,"profile_background_color":"000000","profile_background_image_url":"http:\/\/abs.twimg.com\/images\/themes\/theme14\/bg.gif","profile_background_image_url_https":"https:\/\/abs.twimg.com\/images\/themes\/theme14\/bg.gif","profile_background_tile":false,"profile_image_url":"http:\/\/pbs.twimg.com\/profile_images\/772859507378642944\/H3B02uib_normal.jpg","profile_image_url_https":"https:\/\/pbs.twimg.com\/profile_images\/772859507378642944\/H3B02uib_normal.jpg","profile_banner_url":"https:\/\/pbs.twimg.com\/profile_banners\/2593332564\/1472349226","profile_link_color":"3B94D9","profile_sidebar_border_color":"000000","profile_sidebar_fill_color":"000000","profile_text_color":"000000","profile_use_background_image":false,"has_extended_profile":true,"default_profile":false,"default_profile_image":false,"following":false,"follow_request_sent":false,"notifications":false},"geo":null,"coordinates":null,"place":null,"contributors":null,"is_quote_status":false,"retweet_count":0,"favorite_count":0,"favorited":false,"retweeted":false,"lang":"ko"},{"created_at":"Sun Sep 11 22:13:39 +0000 2016","id":775094983963602945,"id_str":"775094983963602945","text":"\uc2a4\ud0e0 \uc138\ubc88\uc9f8 \uc138\ud2b8 \ubb34\uc870\uac74 \ub530\uc790!! Go get it Stan!@stanwawrinka #USOpen #StanTheMan #Stanimal","truncated":false,"entities":{"hashtags":[{"text":"USOpen","indices":[48,55]},{"text":"StanTheMan","indices":[56,67]},{"text":"Stanimal","indices":[68,77]}],"symbols":[],"user_mentions":[],"urls":[]},"metadata":{"result_type":"recent","iso_language_code":"ko"},"source":"\u003ca href=\"http:\/\/twitter.com\/download\/android\" rel=\"nofollow\"\u003eTwitter for Android\u003c\/a\u003e","in_reply_to_status_id":null,"in_reply_to_status_id_str":null,"in_reply_to_user_id":null,"in_reply_to_user_id_str":null,"in_reply_to_screen_name":null,"user":{"id":2593332564,"id_str":"2593332564","name":"doles","screen_name":"doleshka","location":"","description":"ALO14 \/ JL99 \/ Chelsea FC \/ Rory McIlroy \/ Stanimal & Delpo \/ Packers & Aaron Rodgers","url":null,"entities":{"description":{"urls":[]}},"protected":false,"followers_count":253,"friends_count":405,"listed_count":52,"created_at":"Sat Jun 28 16:31:53 +0000 2014","favourites_count":249,"utc_offset":-10800,"time_zone":"Atlantic Time (Canada)","geo_enabled":false,"verified":false,"statuses_count":16599,"lang":"en","contributors_enabled":false,"is_translator":false,"is_translation_enabled":false,"profile_background_color":"000000","profile_background_image_url":"http:\/\/abs.twimg.com\/images\/themes\/theme14\/bg.gif","profile_background_image_url_https":"https:\/\/abs.twimg.com\/images\/themes\/theme14\/bg.gif","profile_background_tile":false,"profile_image_url":"http:\/\/pbs.twimg.com\/profile_images\/772859507378642944\/H3B02uib_normal.jpg","profile_image_url_https":"https:\/\/pbs.twimg.com\/profile_images\/772859507378642944\/H3B02uib_normal.jpg","profile_banner_url":"https:\/\/pbs.twimg.com\/profile_banners\/2593332564\/1472349226","profile_link_color":"3B94D9","profile_sidebar_border_color":"000000","profile_sidebar_fill_color":"000000","profile_text_color":"000000","profile_use_background_image":false,"has_extended_profile":true,"default_profile":false,"default_profile_image":false,"following":false,"follow_request_sent":false,"notifications":false},"geo":null,"coordinates":null,"place":null,"contributors":null,"is_quote_status":false,"retweet_count":0,"favorite_count":0,"favorited":false,"retweeted":false,"lang":"ko"},{"created_at":"Sun Sep 11 20:02:42 +0000 2016","id":775062028146741248,"id_str":"775062028146741248","text":"\uc5b4\ucc28\ud53c \uc6b0\uc2b9\uc740 \uc870\ucf54\ube44\u314a\uc74d\uc74d #USOpen https:\/\/t.co\/1Z87lYDqHu","truncated":false,"entities":{"hashtags":[{"text":"USOpen","indices":[15,22]}],"symbols":[],"user_mentions":[],"urls":[],"media":[{"id":775062011302424576,"id_str":"775062011302424576","indices":[23,46],"media_url":"http:\/\/pbs.twimg.com\/media\/CsGSyvaUsAAmQhh.jpg","media_url_https":"https:\/\/pbs.twimg.com\/media\/CsGSyvaUsAAmQhh.jpg","url":"https:\/\/t.co\/1Z87lYDqHu","display_url":"pic.twitter.com\/1Z87lYDqHu","expanded_url":"https:\/\/twitter.com\/_mmdm\/status\/775062028146741248\/photo\/1","type":"photo","sizes":{"medium":{"w":1200,"h":675,"resize":"fit"},"small":{"w":680,"h":382,"resize":"fit"},"thumb":{"w":150,"h":150,"resize":"crop"},"large":{"w":1334,"h":750,"resize":"fit"}}}]},"extended_entities":{"media":[{"id":775062011302424576,"id_str":"775062011302424576","indices":[23,46],"media_url":"http:\/\/pbs.twimg.com\/media\/CsGSyvaUsAAmQhh.jpg","media_url_https":"https:\/\/pbs.twimg.com\/media\/CsGSyvaUsAAmQhh.jpg","url":"https:\/\/t.co\/1Z87lYDqHu","display_url":"pic.twitter.com\/1Z87lYDqHu","expanded_url":"https:\/\/twitter.com\/_mmdm\/status\/775062028146741248\/photo\/1","type":"photo","sizes":{"medium":{"w":1200,"h":675,"resize":"fit"},"small":{"w":680,"h":382,"resize":"fit"},"thumb":{"w":150,"h":150,"resize":"crop"},"large":{"w":1334,"h":750,"resize":"fit"}}}]},"metadata":{"result_type":"recent","iso_language_code":"ko"},"source":"\u003ca href=\"http:\/\/twitter.com\/download\/iphone\" rel=\"nofollow\"\u003eTwitter for iPhone\u003c\/a\u003e","in_reply_to_status_id":null,"in_reply_to_status_id_str":null,"in_reply_to_user_id":null,"in_reply_to_user_id_str":null,"in_reply_to_screen_name":null,"user":{"id":2910791341,"id_str":"2910791341","name":"mmdm","screen_name":"_mmdm","location":"","description":"https:\/\/t.co\/Vcwhzrgs1Q","url":"https:\/\/t.co\/J3dC2MHGTj","entities":{"url":{"urls":[{"url":"https:\/\/t.co\/J3dC2MHGTj","expanded_url":"https:\/\/youtu.be\/izSMDlCDXBc","display_url":"youtu.be\/izSMDlCDXBc","indices":[0,23]}]},"description":{"urls":[{"url":"https:\/\/t.co\/Vcwhzrgs1Q","expanded_url":"https:\/\/youtu.be\/UdyIc2pgAoc","display_url":"youtu.be\/UdyIc2pgAoc","indices":[0,23]}]}},"protected":false,"followers_count":2735,"friends_count":391,"listed_count":22,"created_at":"Wed Nov 26 09:47:08 +0000 2014","favourites_count":12678,"utc_offset":-21600,"time_zone":"Central America","geo_enabled":true,"verified":false,"statuses_count":25194,"lang":"en","contributors_enabled":false,"is_translator":false,"is_translation_enabled":false,"profile_background_color":"C0DEED","profile_background_image_url":"http:\/\/pbs.twimg.com\/profile_background_images\/541488604988456962\/4UULyGp-.jpeg","profile_background_image_url_https":"https:\/\/pbs.twimg.com\/profile_background_images\/541488604988456962\/4UULyGp-.jpeg","profile_background_tile":false,"profile_image_url":"http:\/\/pbs.twimg.com\/profile_images\/761052561361076226\/_XQsiAbr_normal.jpg","profile_image_url_https":"https:\/\/pbs.twimg.com\/profile_images\/761052561361076226\/_XQsiAbr_normal.jpg","profile_banner_url":"https:\/\/pbs.twimg.com\/profile_banners\/2910791341\/1470071279","profile_link_color":"1B95E0","profile_sidebar_border_color":"C0DEED","profile_sidebar_fill_color":"DDEEF6","profile_text_color":"333333","profile_use_background_image":false,"has_extended_profile":false,"default_profile":false,"default_profile_image":false,"following":false,"follow_request_sent":false,"notifications":false},"geo":null,"coordinates":null,"place":null,"contributors":null,"is_quote_status":false,"retweet_count":0,"favorite_count":1,"favorited":false,"retweeted":false,"possibly_sensitive":false,"lang":"ko"},{"created_at":"Sat Sep 10 01:45:33 +0000 2016","id":774423533946417152,"id_str":"774423533946417152","text":"\ubc14\ube0c\ub9b0\uce74 #usopen \uacb0\uc2b9\uc9c4\ucd9c! congrats @stanwawrinka \ud83d\udc4f\ud83d\udc4f https:\/\/t.co\/rSzTSeM8RB","truncated":false,"entities":{"hashtags":[{"text":"usopen","indices":[5,12]}],"symbols":[],"user_mentions":[{"screen_name":"stanwawrinka","name":"Stanislas Wawrinka","id":65187067,"id_str":"65187067","indices":[28,41]}],"urls":[{"url":"https:\/\/t.co\/rSzTSeM8RB","expanded_url":"https:\/\/twitter.com\/usopen\/status\/774422189156163584","display_url":"twitter.com\/usopen\/status\/\u2026","indices":[45,68]}]},"metadata":{"result_type":"recent","iso_language_code":"ko"},"source":"\u003ca href=\"http:\/\/twitter.com\/download\/android\" rel=\"nofollow\"\u003eTwitter for Android\u003c\/a\u003e","in_reply_to_status_id":null,"in_reply_to_status_id_str":null,"in_reply_to_user_id":null,"in_reply_to_user_id_str":null,"in_reply_to_screen_name":null,"user":{"id":42845175,"id_str":"42845175","name":"\uc774\ud615\ubbf8","screen_name":"LeeHyungMi","location":"Seoul, Korea","description":"Thank you","url":"http:\/\/t.co\/P1KddofhMe","entities":{"url":{"urls":[{"url":"http:\/\/t.co\/P1KddofhMe","expanded_url":"http:\/\/leehyungmi.wordpress.com","display_url":"leehyungmi.wordpress.com","indices":[0,22]}]},"description":{"urls":[]}},"protected":false,"followers_count":55,"friends_count":81,"listed_count":2,"created_at":"Wed May 27 08:46:17 +0000 2009","favourites_count":138,"utc_offset":32400,"time_zone":"Seoul","geo_enabled":false,"verified":false,"statuses_count":366,"lang":"ko","contributors_enabled":false,"is_translator":false,"is_translation_enabled":false,"profile_background_color":"EDECE9","profile_background_image_url":"http:\/\/abs.twimg.com\/images\/themes\/theme3\/bg.gif","profile_background_image_url_https":"https:\/\/abs.twimg.com\/images\/themes\/theme3\/bg.gif","profile_background_tile":false,"profile_image_url":"http:\/\/pbs.twimg.com\/profile_images\/1130870862\/_______6_normal.jpg","profile_image_url_https":"https:\/\/pbs.twimg.com\/profile_images\/1130870862\/_______6_normal.jpg","profile_link_color":"088253","profile_sidebar_border_color":"D3D2CF","profile_sidebar_fill_color":"E3E2DE","profile_text_color":"634047","profile_use_background_image":true,"has_extended_profile":false,"default_profile":false,"default_profile_image":false,"following":false,"follow_request_sent":false,"notifications":false},"geo":null,"coordinates":null,"place":null,"contributors":null,"is_quote_status":true,"quoted_status_id":774422189156163584,"quoted_status_id_str":"774422189156163584","quoted_status":{"created_at":"Sat Sep 10 01:40:12 +0000 2016","id":774422189156163584,"id_str":"774422189156163584","text":"Welcome to your first #usopen final, @stanwawrinka! \n\nHe defeats #Nishikori 4-6, 7-5, 6-4, 6-2. https:\/\/t.co\/p1LsxsJu8v","truncated":false,"entities":{"hashtags":[{"text":"usopen","indices":[22,29]},{"text":"Nishikori","indices":[65,75]}],"symbols":[],"user_mentions":[{"screen_name":"stanwawrinka","name":"Stanislas Wawrinka","id":65187067,"id_str":"65187067","indices":[37,50]}],"urls":[],"media":[{"id":774421552582434816,"id_str":"774421552582434816","indices":[96,119],"media_url":"http:\/\/pbs.twimg.com\/ext_tw_video_thumb\/774421552582434816\/pu\/img\/vI2ScK0pI5WTWU5U.jpg","media_url_https":"https:\/\/pbs.twimg.com\/ext_tw_video_thumb\/774421552582434816\/pu\/img\/vI2ScK0pI5WTWU5U.jpg","url":"https:\/\/t.co\/p1LsxsJu8v","display_url":"pic.twitter.com\/p1LsxsJu8v","expanded_url":"https:\/\/twitter.com\/usopen\/status\/774422189156163584\/video\/1","type":"photo","sizes":{"thumb":{"w":150,"h":150,"resize":"crop"},"medium":{"w":600,"h":400,"resize":"fit"},"small":{"w":340,"h":227,"resize":"fit"},"large":{"w":1024,"h":683,"resize":"fit"}}}]},"extended_entities":{"media":[{"id":774421552582434816,"id_str":"774421552582434816","indices":[96,119],"media_url":"http:\/\/pbs.twimg.com\/ext_tw_video_thumb\/774421552582434816\/pu\/img\/vI2ScK0pI5WTWU5U.jpg","media_url_https":"https:\/\/pbs.twimg.com\/ext_tw_video_thumb\/774421552582434816\/pu\/img\/vI2ScK0pI5WTWU5U.jpg","url":"https:\/\/t.co\/p1LsxsJu8v","display_url":"pic.twitter.com\/p1LsxsJu8v","expanded_url":"https:\/\/twitter.com\/usopen\/status\/774422189156163584\/video\/1","type":"video","sizes":{"thumb":{"w":150,"h":150,"resize":"crop"},"medium":{"w":600,"h":400,"resize":"fit"},"small":{"w":340,"h":227,"resize":"fit"},"large":{"w":1024,"h":683,"resize":"fit"}},"video_info":{"aspect_ratio":[3,2],"duration_millis":5434,"variants":[{"content_type":"application\/x-mpegURL","url":"https:\/\/video.twimg.com\/ext_tw_video\/774421552582434816\/pu\/pl\/29ERA6pFyNS-3XJk.m3u8"},{"bitrate":2176000,"content_type":"video\/mp4","url":"https:\/\/video.twimg.com\/ext_tw_video\/774421552582434816\/pu\/vid\/1080x720\/Fa9UJpRekK8ZevlV.mp4"},{"content_type":"application\/dash+xml","url":"https:\/\/video.twimg.com\/ext_tw_video\/774421552582434816\/pu\/pl\/29ERA6pFyNS-3XJk.mpd"},{"bitrate":320000,"content_type":"video\/mp4","url":"https:\/\/video.twimg.com\/ext_tw_video\/774421552582434816\/pu\/vid\/270x180\/zCTjKXA0HG2MDlLX.mp4"},{"bitrate":832000,"content_type":"video\/mp4","url":"https:\/\/video.twimg.com\/ext_tw_video\/774421552582434816\/pu\/vid\/540x360\/5ftTEChNk7qEOke_.mp4"}]},"additional_media_info":{"title":"","description":"","embeddable":true,"monetizable":false}}]},"metadata":{"result_type":"recent","iso_language_code":"ko"},"source":"\u003ca href=\"http:\/\/twitter.com\" rel=\"nofollow\"\u003eTwitter Web Client\u003c\/a\u003e","in_reply_to_status_id":null,"in_reply_to_status_id_str":null,"in_reply_to_user_id":null,"in_reply_to_user_id_str":null,"in_reply_to_screen_name":null,"user":{"id":14836197,"id_str":"14836197","name":"US Open Tennis","screen_name":"usopen","location":"Flushing Meadows, New York","description":"Official Twitter of the US Open Tennis Championships | 2016 Dates: 8\/29 - 9\/11 | Terms of Use: https:\/\/t.co\/SXV9s3SLcd | #usopen","url":"http:\/\/t.co\/4Ilr5i7adf","entities":{"url":{"urls":[{"url":"http:\/\/t.co\/4Ilr5i7adf","expanded_url":"http:\/\/www.usopen.org","display_url":"usopen.org","indices":[0,22]}]},"description":{"urls":[{"url":"https:\/\/t.co\/SXV9s3SLcd","expanded_url":"http:\/\/bit.ly\/2bLWjNB","display_url":"bit.ly\/2bLWjNB","indices":[95,118]}]}},"protected":false,"followers_count":1187552,"friends_count":2390,"listed_count":8606,"created_at":"Mon May 19 18:35:03 +0000 2008","favourites_count":13959,"utc_offset":-14400,"time_zone":"Eastern Time (US & Canada)","geo_enabled":true,"verified":true,"statuses_count":21790,"lang":"en","contributors_enabled":false,"is_translator":false,"is_translation_enabled":false,"profile_background_color":"004B85","profile_background_image_url":"http:\/\/pbs.twimg.com\/profile_background_images\/643265509073514496\/q9jGC2Qe.jpg","profile_background_image_url_https":"https:\/\/pbs.twimg.com\/profile_background_images\/643265509073514496\/q9jGC2Qe.jpg","profile_background_tile":false,"profile_image_url":"http:\/\/pbs.twimg.com\/profile_images\/643265101357797376\/oMuUZQHZ_normal.jpg","profile_image_url_https":"https:\/\/pbs.twimg.com\/profile_images\/643265101357797376\/oMuUZQHZ_normal.jpg","profile_banner_url":"https:\/\/pbs.twimg.com\/profile_banners\/14836197\/1473648666","profile_link_color":"0090FF","profile_sidebar_border_color":"FFFFFF","profile_sidebar_fill_color":"252429","profile_text_color":"666666","profile_use_background_image":true,"has_extended_profile":false,"default_profile":false,"default_profile_image":false,"following":false,"follow_request_sent":false,"notifications":false},"geo":null,"coordinates":null,"place":null,"contributors":null,"is_quote_status":false,"retweet_count":1123,"favorite_count":1465,"favorited":false,"retweeted":false,"possibly_sensitive":false,"lang":"en"},"retweet_count":0,"favorite_count":0,"favorited":false,"retweeted":false,"possibly_sensitive":false,"lang":"ko"},{"created_at":"Sat Sep 10 01:43:34 +0000 2016","id":774423034706788352,"id_str":"774423034706788352","text":"#usopen \ud30c\uc774\ub110\uc774 \uc870\ucf54\ube44\uce58 v. \ubc14\ube0c\ub9b0\uce74 \ub77c\ub2c8, \uc804\ud600 \ubc14\ub77c\uc9c0 \uc54a\uc558\ub358 \uc870\ud569\uc774\ub2e4\u2026","truncated":false,"entities":{"hashtags":[{"text":"usopen","indices":[0,7]}],"symbols":[],"user_mentions":[],"urls":[]},"metadata":{"result_type":"recent","iso_language_code":"ko"},"source":"\u003ca href=\"http:\/\/twitter.com\/download\/iphone\" rel=\"nofollow\"\u003eTwitter for iPhone\u003c\/a\u003e","in_reply_to_status_id":null,"in_reply_to_status_id_str":null,"in_reply_to_user_id":null,"in_reply_to_user_id_str":null,"in_reply_to_screen_name":null,"user":{"id":31789905,"id_str":"31789905","name":"Hyoung-Won Park","screen_name":"dalcrose","location":"South Korea","description":"Anything else, La vie et tout le reste. RT \u2260 endorsement. PGP: 0x41EDF5CE","url":"https:\/\/t.co\/WDniBlQbrj","entities":{"url":{"urls":[{"url":"https:\/\/t.co\/WDniBlQbrj","expanded_url":"http:\/\/dalcrose.tumblr.com","display_url":"dalcrose.tumblr.com","indices":[0,23]}]},"description":{"urls":[]}},"protected":false,"followers_count":1255,"friends_count":1543,"listed_count":94,"created_at":"Thu Apr 16 13:36:19 +0000 2009","favourites_count":72148,"utc_offset":32400,"time_zone":"Seoul","geo_enabled":true,"verified":false,"statuses_count":45328,"lang":"en","contributors_enabled":false,"is_translator":false,"is_translation_enabled":false,"profile_background_color":"709397","profile_background_image_url":"http:\/\/pbs.twimg.com\/profile_background_images\/675518890\/74c77d9a2c6b874c9eae76536404813a.jpeg","profile_background_image_url_https":"https:\/\/pbs.twimg.com\/profile_background_images\/675518890\/74c77d9a2c6b874c9eae76536404813a.jpeg","profile_background_tile":true,"profile_image_url":"http:\/\/pbs.twimg.com\/profile_images\/1182316531\/dalcrose_AI_Final_normal.png","profile_image_url_https":"https:\/\/pbs.twimg.com\/profile_images\/1182316531\/dalcrose_AI_Final_normal.png","profile_banner_url":"https:\/\/pbs.twimg.com\/profile_banners\/31789905\/1401423242","profile_link_color":"2683D4","profile_sidebar_border_color":"000000","profile_sidebar_fill_color":"A0C5C7","profile_text_color":"333333","profile_use_background_image":true,"has_extended_profile":true,"default_profile":false,"default_profile_image":false,"following":false,"follow_request_sent":false,"notifications":false},"geo":null,"coordinates":null,"place":null,"contributors":null,"is_quote_status":false,"retweet_count":0,"favorite_count":0,"favorited":false,"retweeted":false,"lang":"ko"},{"created_at":"Sat Sep 10 00:14:49 +0000 2016","id":774400703057965057,"id_str":"774400703057965057","text":"\uacfc\uc5f0 #usopen final \uc740 \n\ub2c8\uc2dc\ucf54\ub9ac vs \uc870\ucf54\ube44\uce58\uc77c\uae4c\n\ubc14\ube0c\ub9b0\uce74 vs \uc870\ucf54\ube44\uce58\uc77c\uae4c","truncated":false,"entities":{"hashtags":[{"text":"usopen","indices":[3,10]}],"symbols":[],"user_mentions":[],"urls":[]},"metadata":{"result_type":"recent","iso_language_code":"ko"},"source":"\u003ca href=\"http:\/\/twitter.com\/download\/iphone\" rel=\"nofollow\"\u003eTwitter for iPhone\u003c\/a\u003e","in_reply_to_status_id":null,"in_reply_to_status_id_str":null,"in_reply_to_user_id":null,"in_reply_to_user_id_str":null,"in_reply_to_screen_name":null,"user":{"id":151817168,"id_str":"151817168","name":"park jinn","screen_name":"veryveryjin","location":"","description":"a realistic optimist, sophisticated individualist (\uac1c\uc778, \ub300\ud654 \uba58\uc158\uc740 \ub0a8\uae30\uace0 \uc2f6\uc740 \uac83\ub9cc \ub0a8\uae30\uace0 \ud2c8\ud2c8\ud788 \ub610\ub294 \ubd80\uc9c0\ub7f0\ud788 \uc9c0\uc6c1\ub2c8\ub2e4)","url":"https:\/\/t.co\/NS89A5KDcU","entities":{"url":{"urls":[{"url":"https:\/\/t.co\/NS89A5KDcU","expanded_url":"http:\/\/Instagram.com\/veryveryjin","display_url":"Instagram.com\/veryveryjin","indices":[0,23]}]},"description":{"urls":[]}},"protected":false,"followers_count":362,"friends_count":483,"listed_count":10,"created_at":"Fri Jun 04 09:30:38 +0000 2010","favourites_count":556,"utc_offset":null,"time_zone":null,"geo_enabled":true,"verified":false,"statuses_count":2911,"lang":"en","contributors_enabled":false,"is_translator":false,"is_translation_enabled":false,"profile_background_color":"EADFF2","profile_background_image_url":"http:\/\/abs.twimg.com\/images\/themes\/theme10\/bg.gif","profile_background_image_url_https":"https:\/\/abs.twimg.com\/images\/themes\/theme10\/bg.gif","profile_background_tile":true,"profile_image_url":"http:\/\/pbs.twimg.com\/profile_images\/775712949944000512\/TekBqmSd_normal.jpg","profile_image_url_https":"https:\/\/pbs.twimg.com\/profile_images\/775712949944000512\/TekBqmSd_normal.jpg","profile_banner_url":"https:\/\/pbs.twimg.com\/profile_banners\/151817168\/1435676458","profile_link_color":"B774DE","profile_sidebar_border_color":"65B0DA","profile_sidebar_fill_color":"DBDBDB","profile_text_color":"3D1957","profile_use_background_image":true,"has_extended_profile":false,"default_profile":false,"default_profile_image":false,"following":false,"follow_request_sent":false,"notifications":false},"geo":null,"coordinates":null,"place":{"id":"0118caea4a6876c6","url":"https:\/\/api.twitter.com\/1.1\/geo\/id\/0118caea4a6876c6.json","place_type":"city","name":"Yongsan-gu","full_name":"Yongsan-gu, Republic of Korea","country_code":"KR","country":"Republic of Korea","contained_within":[],"bounding_box":{"type":"Polygon","coordinates":[[[126.948708198697,37.505957133047],[127.011971399668,37.505957133047],[127.011971399668,37.5481625308819],[126.948708198697,37.5481625308819]]]},"attributes":{}},"contributors":null,"is_quote_status":false,"retweet_count":0,"favorite_count":0,"favorited":false,"retweeted":false,"lang":"ko"},{"created_at":"Fri Sep 09 12:56:24 +0000 2016","id":774229973649338368,"id_str":"774229973649338368","text":"RT @MOFU_terro: (\u0e51\u2180\u11ba\u2180\u0e51)\u2604 #IS #ISIS #ISIL #Deash #IslamicState #\u062f\u0627\u0639\u0634 #\u0627\u0644\u062f\u0648\u0644\u0629_\u0627\u0644\u0625\u0633\u0644\u0627\u0645\u064a\u0629 #\u0627\u0644\u062f\u0648\u0644\u0629 https:\/\/t.co\/f6y4B1Xap5","truncated":false,"entities":{"hashtags":[{"text":"IS","indices":[25,28]},{"text":"ISIS","indices":[29,34]},{"text":"ISIL","indices":[35,40]},{"text":"Deash","indices":[41,47]},{"text":"IslamicState","indices":[48,61]},{"text":"\u062f\u0627\u0639\u0634","indices":[62,67]},{"text":"\u0627\u0644\u062f\u0648\u0644\u0629_\u0627\u0644\u0625\u0633\u0644\u0627\u0645\u064a\u0629","indices":[68,85]},{"text":"\u0627\u0644\u062f\u0648\u0644\u0629","indices":[86,93]}],"symbols":[],"user_mentions":[{"screen_name":"MOFU_terro","name":"\u30e2\u30d5\u30c6\u30edbot","id":3486272594,"id_str":"3486272594","indices":[3,14]}],"urls":[],"media":[{"id":649135748138954752,"id_str":"649135748138954752","indices":[94,117],"media_url":"http:\/\/pbs.twimg.com\/media\/CQIxhg7UcAAkyXw.jpg","media_url_https":"https:\/\/pbs.twimg.com\/media\/CQIxhg7UcAAkyXw.jpg","url":"https:\/\/t.co\/f6y4B1Xap5","display_url":"pic.twitter.com\/f6y4B1Xap5","expanded_url":"http:\/\/twitter.com\/MOFU_terro\/status\/649135749032312832\/photo\/1","type":"photo","sizes":{"medium":{"w":481,"h":376,"resize":"fit"},"thumb":{"w":150,"h":150,"resize":"crop"},"small":{"w":340,"h":266,"resize":"fit"},"large":{"w":481,"h":376,"resize":"fit"}},"source_status_id":649135749032312832,"source_status_id_str":"649135749032312832","source_user_id":3486272594,"source_user_id_str":"3486272594"}]},"extended_entities":{"media":[{"id":649135748138954752,"id_str":"649135748138954752","indices":[94,117],"media_url":"http:\/\/pbs.twimg.com\/media\/CQIxhg7UcAAkyXw.jpg","media_url_https":"https:\/\/pbs.twimg.com\/media\/CQIxhg7UcAAkyXw.jpg","url":"https:\/\/t.co\/f6y4B1Xap5","display_url":"pic.twitter.com\/f6y4B1Xap5","expanded_url":"http:\/\/twitter.com\/MOFU_terro\/status\/649135749032312832\/photo\/1","type":"photo","sizes":{"medium":{"w":481,"h":376,"resize":"fit"},"thumb":{"w":150,"h":150,"resize":"crop"},"small":{"w":340,"h":266,"resize":"fit"},"large":{"w":481,"h":376,"resize":"fit"}},"source_status_id":649135749032312832,"source_status_id_str":"649135749032312832","source_user_id":3486272594,"source_user_id_str":"3486272594"}]},"metadata":{"result_type":"recent","iso_language_code":"ko"},"source":"\u003ca href=\"http:\/\/www.floodgap.com\/software\/ttytter\/\" rel=\"nofollow\"\u003eTTYtter\u003c\/a\u003e","in_reply_to_status_id":null,"in_reply_to_status_id_str":null,"in_reply_to_user_id":null,"in_reply_to_user_id_str":null,"in_reply_to_screen_name":null,"user":{"id":4329580222,"id_str":"4329580222","name":"\u30b3\u30a2\u30e9\u3061\u3083\u3093","screen_name":"Koala870","location":"","description":"\u30e6\u30fc\u30ab\u30ea\u306e\u8449\u3063\u3071\u98df\u3079\u3066\u5bdd\u308b\u306e\u304c\u5927\u597d\u304d\u3002\u610f\u5916\u3068\u307c\u304f\u3082\u30e2\u30d5\u30e2\u30d5\u3060\u3088\u3002\n#\u30b3\u30a2\u30e9 #koala","url":null,"entities":{"description":{"urls":[]}},"protected":false,"followers_count":572,"friends_count":656,"listed_count":34,"created_at":"Mon Nov 30 14:00:51 +0000 2015","favourites_count":0,"utc_offset":32400,"time_zone":"Tokyo","geo_enabled":false,"verified":false,"statuses_count":19369,"lang":"ja","contributors_enabled":false,"is_translator":false,"is_translation_enabled":false,"profile_background_color":"000000","profile_background_image_url":"http:\/\/abs.twimg.com\/images\/themes\/theme1\/bg.png","profile_background_image_url_https":"https:\/\/abs.twimg.com\/images\/themes\/theme1\/bg.png","profile_background_tile":false,"profile_image_url":"http:\/\/pbs.twimg.com\/profile_images\/671374440253427714\/U1fuYxi5_normal.jpg","profile_image_url_https":"https:\/\/pbs.twimg.com\/profile_images\/671374440253427714\/U1fuYxi5_normal.jpg","profile_banner_url":"https:\/\/pbs.twimg.com\/profile_banners\/4329580222\/1448902041","profile_link_color":"F5ABB5","profile_sidebar_border_color":"000000","profile_sidebar_fill_color":"000000","profile_text_color":"000000","profile_use_background_image":false,"has_extended_profile":false,"default_profile":false,"default_profile_image":false,"following":false,"follow_request_sent":false,"notifications":false},"geo":null,"coordinates":null,"place":null,"contributors":null,"retweeted_status":{"created_at":"Fri Sep 09 09:02:53 +0000 2016","id":774171204286459904,"id_str":"774171204286459904","text":"(\u0e51\u2180\u11ba\u2180\u0e51)\u2604 #IS #ISIS #ISIL #Deash #IslamicState #\u062f\u0627\u0639\u0634 #\u0627\u0644\u062f\u0648\u0644\u0629_\u0627\u0644\u0625\u0633\u0644\u0627\u0645\u064a\u0629 #\u0627\u0644\u062f\u0648\u0644\u0629 https:\/\/t.co\/f6y4B1Xap5","truncated":false,"entities":{"hashtags":[{"text":"IS","indices":[9,12]},{"text":"ISIS","indices":[13,18]},{"text":"ISIL","indices":[19,24]},{"text":"Deash","indices":[25,31]},{"text":"IslamicState","indices":[32,45]},{"text":"\u062f\u0627\u0639\u0634","indices":[46,51]},{"text":"\u0627\u0644\u062f\u0648\u0644\u0629_\u0627\u0644\u0625\u0633\u0644\u0627\u0645\u064a\u0629","indices":[52,69]},{"text":"\u0627\u0644\u062f\u0648\u0644\u0629","indices":[70,77]}],"symbols":[],"user_mentions":[],"urls":[],"media":[{"id":649135748138954752,"id_str":"649135748138954752","indices":[78,101],"media_url":"http:\/\/pbs.twimg.com\/media\/CQIxhg7UcAAkyXw.jpg","media_url_https":"https:\/\/pbs.twimg.com\/media\/CQIxhg7UcAAkyXw.jpg","url":"https:\/\/t.co\/f6y4B1Xap5","display_url":"pic.twitter.com\/f6y4B1Xap5","expanded_url":"http:\/\/twitter.com\/MOFU_terro\/status\/649135749032312832\/photo\/1","type":"photo","sizes":{"medium":{"w":481,"h":376,"resize":"fit"},"thumb":{"w":150,"h":150,"resize":"crop"},"small":{"w":340,"h":266,"resize":"fit"},"large":{"w":481,"h":376,"resize":"fit"}},"source_status_id":649135749032312832,"source_status_id_str":"649135749032312832","source_user_id":3486272594,"source_user_id_str":"3486272594"}]},"extended_entities":{"media":[{"id":649135748138954752,"id_str":"649135748138954752","indices":[78,101],"media_url":"http:\/\/pbs.twimg.com\/media\/CQIxhg7UcAAkyXw.jpg","media_url_https":"https:\/\/pbs.twimg.com\/media\/CQIxhg7UcAAkyXw.jpg","url":"https:\/\/t.co\/f6y4B1Xap5","display_url":"pic.twitter.com\/f6y4B1Xap5","expanded_url":"http:\/\/twitter.com\/MOFU_terro\/status\/649135749032312832\/photo\/1","type":"photo","sizes":{"medium":{"w":481,"h":376,"resize":"fit"},"thumb":{"w":150,"h":150,"resize":"crop"},"small":{"w":340,"h":266,"resize":"fit"},"large":{"w":481,"h":376,"resize":"fit"}},"source_status_id":649135749032312832,"source_status_id_str":"649135749032312832","source_user_id":3486272594,"source_user_id_str":"3486272594"}]},"metadata":{"result_type":"recent","iso_language_code":"ko"},"source":"\u003ca href=\"http:\/\/rakubots.kissa.jp\/\" rel=\"nofollow\"\u003erakubo2\u003c\/a\u003e","in_reply_to_status_id":null,"in_reply_to_status_id_str":null,"in_reply_to_user_id":null,"in_reply_to_user_id_str":null,"in_reply_to_screen_name":null,"user":{"id":3486272594,"id_str":"3486272594","name":"\u30e2\u30d5\u30c6\u30edbot","screen_name":"MOFU_terro","location":"\u306d\u3053\u5927\u597d\u304d","description":"\u6211\u3005\u306e\u7a76\u6975\u7684\u306a\u76ee\u6a19\u306f\u7121\u6148\u60b2\u306a\u30e2\u30d5\u30e2\u30d5\u6c5a\u67d3\u3067\u3042\u308b #ISIS\u3061\u3083\u3093 #ISISchan #ISIS_chan #\u732b #\u732b\u753b\u50cf","url":null,"entities":{"description":{"urls":[]}},"protected":false,"followers_count":534,"friends_count":529,"listed_count":9,"created_at":"Mon Sep 07 22:15:33 +0000 2015","favourites_count":225,"utc_offset":-25200,"time_zone":"Pacific Time (US & Canada)","geo_enabled":false,"verified":false,"statuses_count":5701,"lang":"ja","contributors_enabled":false,"is_translator":false,"is_translation_enabled":false,"profile_background_color":"C0DEED","profile_background_image_url":"http:\/\/abs.twimg.com\/images\/themes\/theme1\/bg.png","profile_background_image_url_https":"https:\/\/abs.twimg.com\/images\/themes\/theme1\/bg.png","profile_background_tile":false,"profile_image_url":"http:\/\/pbs.twimg.com\/profile_images\/641012457910091776\/SK4aML6w_normal.jpg","profile_image_url_https":"https:\/\/pbs.twimg.com\/profile_images\/641012457910091776\/SK4aML6w_normal.jpg","profile_banner_url":"https:\/\/pbs.twimg.com\/profile_banners\/3486272594\/1441664533","profile_link_color":"0084B4","profile_sidebar_border_color":"C0DEED","profile_sidebar_fill_color":"DDEEF6","profile_text_color":"333333","profile_use_background_image":true,"has_extended_profile":false,"default_profile":true,"default_profile_image":false,"following":false,"follow_request_sent":false,"notifications":false},"geo":null,"coordinates":null,"place":null,"contributors":null,"is_quote_status":false,"retweet_count":3,"favorite_count":0,"favorited":false,"retweeted":false,"possibly_sensitive":false,"lang":"ko"},"is_quote_status":false,"retweet_count":3,"favorite_count":0,"favorited":false,"retweeted":false,"possibly_sensitive":false,"lang":"ko"},{"created_at":"Fri Sep 09 10:56:45 +0000 2016","id":774199859553275904,"id_str":"774199859553275904","text":"RT @MOFU_terro: (\u0e51\u2180\u11ba\u2180\u0e51)\u2604 #IS #ISIS #ISIL #Deash #IslamicState #\u062f\u0627\u0639\u0634 #\u0627\u0644\u062f\u0648\u0644\u0629_\u0627\u0644\u0625\u0633\u0644\u0627\u0645\u064a\u0629 #\u0627\u0644\u062f\u0648\u0644\u0629 https:\/\/t.co\/f6y4B1Xap5","truncated":false,"entities":{"hashtags":[{"text":"IS","indices":[25,28]},{"text":"ISIS","indices":[29,34]},{"text":"ISIL","indices":[35,40]},{"text":"Deash","indices":[41,47]},{"text":"IslamicState","indices":[48,61]},{"text":"\u062f\u0627\u0639\u0634","indices":[62,67]},{"text":"\u0627\u0644\u062f\u0648\u0644\u0629_\u0627\u0644\u0625\u0633\u0644\u0627\u0645\u064a\u0629","indices":[68,85]},{"text":"\u0627\u0644\u062f\u0648\u0644\u0629","indices":[86,93]}],"symbols":[],"user_mentions":[{"screen_name":"MOFU_terro","name":"\u30e2\u30d5\u30c6\u30edbot","id":3486272594,"id_str":"3486272594","indices":[3,14]}],"urls":[],"media":[{"id":649135748138954752,"id_str":"649135748138954752","indices":[94,117],"media_url":"http:\/\/pbs.twimg.com\/media\/CQIxhg7UcAAkyXw.jpg","media_url_https":"https:\/\/pbs.twimg.com\/media\/CQIxhg7UcAAkyXw.jpg","url":"https:\/\/t.co\/f6y4B1Xap5","display_url":"pic.twitter.com\/f6y4B1Xap5","expanded_url":"http:\/\/twitter.com\/MOFU_terro\/status\/649135749032312832\/photo\/1","type":"photo","sizes":{"medium":{"w":481,"h":376,"resize":"fit"},"thumb":{"w":150,"h":150,"resize":"crop"},"small":{"w":340,"h":266,"resize":"fit"},"large":{"w":481,"h":376,"resize":"fit"}},"source_status_id":649135749032312832,"source_status_id_str":"649135749032312832","source_user_id":3486272594,"source_user_id_str":"3486272594"}]},"extended_entities":{"media":[{"id":649135748138954752,"id_str":"649135748138954752","indices":[94,117],"media_url":"http:\/\/pbs.twimg.com\/media\/CQIxhg7UcAAkyXw.jpg","media_url_https":"https:\/\/pbs.twimg.com\/media\/CQIxhg7UcAAkyXw.jpg","url":"https:\/\/t.co\/f6y4B1Xap5","display_url":"pic.twitter.com\/f6y4B1Xap5","expanded_url":"http:\/\/twitter.com\/MOFU_terro\/status\/649135749032312832\/photo\/1","type":"photo","sizes":{"medium":{"w":481,"h":376,"resize":"fit"},"thumb":{"w":150,"h":150,"resize":"crop"},"small":{"w":340,"h":266,"resize":"fit"},"large":{"w":481,"h":376,"resize":"fit"}},"source_status_id":649135749032312832,"source_status_id_str":"649135749032312832","source_user_id":3486272594,"source_user_id_str":"3486272594"}]},"metadata":{"result_type":"recent","iso_language_code":"ko"},"source":"\u003ca href=\"http:\/\/www.floodgap.com\/software\/ttytter\/\" rel=\"nofollow\"\u003eTTYtter\u003c\/a\u003e","in_reply_to_status_id":null,"in_reply_to_status_id_str":null,"in_reply_to_user_id":null,"in_reply_to_user_id_str":null,"in_reply_to_screen_name":null,"user":{"id":4307944648,"id_str":"4307944648","name":"\u3051\u308d\u3084\u3093","screen_name":"Kerota536","location":"","description":"\u53ef\u611b\u3044\u30ab\u30a8\u30eb\u305f\u3061\u306e\u753b\u50cf\u3092\u3064\u3076\u3084\u304d\u307e\u3059 #\u30ab\u30a8\u30eb #\u304b\u3048\u308b #\u86d9 #frog","url":null,"entities":{"description":{"urls":[]}},"protected":false,"followers_count":509,"friends_count":609,"listed_count":45,"created_at":"Sat Nov 28 14:20:25 +0000 2015","favourites_count":0,"utc_offset":32400,"time_zone":"Tokyo","geo_enabled":false,"verified":false,"statuses_count":18537,"lang":"ja","contributors_enabled":false,"is_translator":false,"is_translation_enabled":false,"profile_background_color":"000000","profile_background_image_url":"http:\/\/abs.twimg.com\/images\/themes\/theme1\/bg.png","profile_background_image_url_https":"https:\/\/abs.twimg.com\/images\/themes\/theme1\/bg.png","profile_background_tile":false,"profile_image_url":"http:\/\/pbs.twimg.com\/profile_images\/670986508615094273\/71QoghGj_normal.jpg","profile_image_url_https":"https:\/\/pbs.twimg.com\/profile_images\/670986508615094273\/71QoghGj_normal.jpg","profile_banner_url":"https:\/\/pbs.twimg.com\/profile_banners\/4307944648\/1448810566","profile_link_color":"4A913C","profile_sidebar_border_color":"000000","profile_sidebar_fill_color":"000000","profile_text_color":"000000","profile_use_background_image":false,"has_extended_profile":false,"default_profile":false,"default_profile_image":false,"following":false,"follow_request_sent":false,"notifications":false},"geo":null,"coordinates":null,"place":null,"contributors":null,"retweeted_status":{"created_at":"Fri Sep 09 09:02:53 +0000 2016","id":774171204286459904,"id_str":"774171204286459904","text":"(\u0e51\u2180\u11ba\u2180\u0e51)\u2604 #IS #ISIS #ISIL #Deash #IslamicState #\u062f\u0627\u0639\u0634 #\u0627\u0644\u062f\u0648\u0644\u0629_\u0627\u0644\u0625\u0633\u0644\u0627\u0645\u064a\u0629 #\u0627\u0644\u062f\u0648\u0644\u0629 https:\/\/t.co\/f6y4B1Xap5","truncated":false,"entities":{"hashtags":[{"text":"IS","indices":[9,12]},{"text":"ISIS","indices":[13,18]},{"text":"ISIL","indices":[19,24]},{"text":"Deash","indices":[25,31]},{"text":"IslamicState","indices":[32,45]},{"text":"\u062f\u0627\u0639\u0634","indices":[46,51]},{"text":"\u0627\u0644\u062f\u0648\u0644\u0629_\u0627\u0644\u0625\u0633\u0644\u0627\u0645\u064a\u0629","indices":[52,69]},{"text":"\u0627\u0644\u062f\u0648\u0644\u0629","indices":[70,77]}],"symbols":[],"user_mentions":[],"urls":[],"media":[{"id":649135748138954752,"id_str":"649135748138954752","indices":[78,101],"media_url":"http:\/\/pbs.twimg.com\/media\/CQIxhg7UcAAkyXw.jpg","media_url_https":"https:\/\/pbs.twimg.com\/media\/CQIxhg7UcAAkyXw.jpg","url":"https:\/\/t.co\/f6y4B1Xap5","display_url":"pic.twitter.com\/f6y4B1Xap5","expanded_url":"http:\/\/twitter.com\/MOFU_terro\/status\/649135749032312832\/photo\/1","type":"photo","sizes":{"medium":{"w":481,"h":376,"resize":"fit"},"thumb":{"w":150,"h":150,"resize":"crop"},"small":{"w":340,"h":266,"resize":"fit"},"large":{"w":481,"h":376,"resize":"fit"}},"source_status_id":649135749032312832,"source_status_id_str":"649135749032312832","source_user_id":3486272594,"source_user_id_str":"3486272594"}]},"extended_entities":{"media":[{"id":649135748138954752,"id_str":"649135748138954752","indices":[78,101],"media_url":"http:\/\/pbs.twimg.com\/media\/CQIxhg7UcAAkyXw.jpg","media_url_https":"https:\/\/pbs.twimg.com\/media\/CQIxhg7UcAAkyXw.jpg","url":"https:\/\/t.co\/f6y4B1Xap5","display_url":"pic.twitter.com\/f6y4B1Xap5","expanded_url":"http:\/\/twitter.com\/MOFU_terro\/status\/649135749032312832\/photo\/1","type":"photo","sizes":{"medium":{"w":481,"h":376,"resize":"fit"},"thumb":{"w":150,"h":150,"resize":"crop"},"small":{"w":340,"h":266,"resize":"fit"},"large":{"w":481,"h":376,"resize":"fit"}},"source_status_id":649135749032312832,"source_status_id_str":"649135749032312832","source_user_id":3486272594,"source_user_id_str":"3486272594"}]},"metadata":{"result_type":"recent","iso_language_code":"ko"},"source":"\u003ca href=\"http:\/\/rakubots.kissa.jp\/\" rel=\"nofollow\"\u003erakubo2\u003c\/a\u003e","in_reply_to_status_id":null,"in_reply_to_status_id_str":null,"in_reply_to_user_id":null,"in_reply_to_user_id_str":null,"in_reply_to_screen_name":null,"user":{"id":3486272594,"id_str":"3486272594","name":"\u30e2\u30d5\u30c6\u30edbot","screen_name":"MOFU_terro","location":"\u306d\u3053\u5927\u597d\u304d","description":"\u6211\u3005\u306e\u7a76\u6975\u7684\u306a\u76ee\u6a19\u306f\u7121\u6148\u60b2\u306a\u30e2\u30d5\u30e2\u30d5\u6c5a\u67d3\u3067\u3042\u308b #ISIS\u3061\u3083\u3093 #ISISchan #ISIS_chan #\u732b #\u732b\u753b\u50cf","url":null,"entities":{"description":{"urls":[]}},"protected":false,"followers_count":534,"friends_count":529,"listed_count":9,"created_at":"Mon Sep 07 22:15:33 +0000 2015","favourites_count":225,"utc_offset":-25200,"time_zone":"Pacific Time (US & Canada)","geo_enabled":false,"verified":false,"statuses_count":5701,"lang":"ja","contributors_enabled":false,"is_translator":false,"is_translation_enabled":false,"profile_background_color":"C0DEED","profile_background_image_url":"http:\/\/abs.twimg.com\/images\/themes\/theme1\/bg.png","profile_background_image_url_https":"https:\/\/abs.twimg.com\/images\/themes\/theme1\/bg.png","profile_background_tile":false,"profile_image_url":"http:\/\/pbs.twimg.com\/profile_images\/641012457910091776\/SK4aML6w_normal.jpg","profile_image_url_https":"https:\/\/pbs.twimg.com\/profile_images\/641012457910091776\/SK4aML6w_normal.jpg","profile_banner_url":"https:\/\/pbs.twimg.com\/profile_banners\/3486272594\/1441664533","profile_link_color":"0084B4","profile_sidebar_border_color":"C0DEED","profile_sidebar_fill_color":"DDEEF6","profile_text_color":"333333","profile_use_background_image":true,"has_extended_profile":false,"default_profile":true,"default_profile_image":false,"following":false,"follow_request_sent":false,"notifications":false},"geo":null,"coordinates":null,"place":null,"contributors":null,"is_quote_status":false,"retweet_count":3,"favorite_count":0,"favorited":false,"retweeted":false,"possibly_sensitive":false,"lang":"ko"},"is_quote_status":false,"retweet_count":3,"favorite_count":0,"favorited":false,"retweeted":false,"possibly_sensitive":false,"lang":"ko"},{"created_at":"Fri Sep 09 09:02:53 +0000 2016","id":774171204286459904,"id_str":"774171204286459904","text":"(\u0e51\u2180\u11ba\u2180\u0e51)\u2604 #IS #ISIS #ISIL #Deash #IslamicState #\u062f\u0627\u0639\u0634 #\u0627\u0644\u062f\u0648\u0644\u0629_\u0627\u0644\u0625\u0633\u0644\u0627\u0645\u064a\u0629 #\u0627\u0644\u062f\u0648\u0644\u0629 https:\/\/t.co\/f6y4B1Xap5","truncated":false,"entities":{"hashtags":[{"text":"IS","indices":[9,12]},{"text":"ISIS","indices":[13,18]},{"text":"ISIL","indices":[19,24]},{"text":"Deash","indices":[25,31]},{"text":"IslamicState","indices":[32,45]},{"text":"\u062f\u0627\u0639\u0634","indices":[46,51]},{"text":"\u0627\u0644\u062f\u0648\u0644\u0629_\u0627\u0644\u0625\u0633\u0644\u0627\u0645\u064a\u0629","indices":[52,69]},{"text":"\u0627\u0644\u062f\u0648\u0644\u0629","indices":[70,77]}],"symbols":[],"user_mentions":[],"urls":[],"media":[{"id":649135748138954752,"id_str":"649135748138954752","indices":[78,101],"media_url":"http:\/\/pbs.twimg.com\/media\/CQIxhg7UcAAkyXw.jpg","media_url_https":"https:\/\/pbs.twimg.com\/media\/CQIxhg7UcAAkyXw.jpg","url":"https:\/\/t.co\/f6y4B1Xap5","display_url":"pic.twitter.com\/f6y4B1Xap5","expanded_url":"http:\/\/twitter.com\/MOFU_terro\/status\/649135749032312832\/photo\/1","type":"photo","sizes":{"medium":{"w":481,"h":376,"resize":"fit"},"thumb":{"w":150,"h":150,"resize":"crop"},"small":{"w":340,"h":266,"resize":"fit"},"large":{"w":481,"h":376,"resize":"fit"}},"source_status_id":649135749032312832,"source_status_id_str":"649135749032312832","source_user_id":3486272594,"source_user_id_str":"3486272594"}]},"extended_entities":{"media":[{"id":649135748138954752,"id_str":"649135748138954752","indices":[78,101],"media_url":"http:\/\/pbs.twimg.com\/media\/CQIxhg7UcAAkyXw.jpg","media_url_https":"https:\/\/pbs.twimg.com\/media\/CQIxhg7UcAAkyXw.jpg","url":"https:\/\/t.co\/f6y4B1Xap5","display_url":"pic.twitter.com\/f6y4B1Xap5","expanded_url":"http:\/\/twitter.com\/MOFU_terro\/status\/649135749032312832\/photo\/1","type":"photo","sizes":{"medium":{"w":481,"h":376,"resize":"fit"},"thumb":{"w":150,"h":150,"resize":"crop"},"small":{"w":340,"h":266,"resize":"fit"},"large":{"w":481,"h":376,"resize":"fit"}},"source_status_id":649135749032312832,"source_status_id_str":"649135749032312832","source_user_id":3486272594,"source_user_id_str":"3486272594"}]},"metadata":{"result_type":"recent","iso_language_code":"ko"},"source":"\u003ca href=\"http:\/\/rakubots.kissa.jp\/\" rel=\"nofollow\"\u003erakubo2\u003c\/a\u003e","in_reply_to_status_id":null,"in_reply_to_status_id_str":null,"in_reply_to_user_id":null,"in_reply_to_user_id_str":null,"in_reply_to_screen_name":null,"user":{"id":3486272594,"id_str":"3486272594","name":"\u30e2\u30d5\u30c6\u30edbot","screen_name":"MOFU_terro","location":"\u306d\u3053\u5927\u597d\u304d","description":"\u6211\u3005\u306e\u7a76\u6975\u7684\u306a\u76ee\u6a19\u306f\u7121\u6148\u60b2\u306a\u30e2\u30d5\u30e2\u30d5\u6c5a\u67d3\u3067\u3042\u308b #ISIS\u3061\u3083\u3093 #ISISchan #ISIS_chan #\u732b #\u732b\u753b\u50cf","url":null,"entities":{"description":{"urls":[]}},"protected":false,"followers_count":534,"friends_count":529,"listed_count":9,"created_at":"Mon Sep 07 22:15:33 +0000 2015","favourites_count":225,"utc_offset":-25200,"time_zone":"Pacific Time (US & Canada)","geo_enabled":false,"verified":false,"statuses_count":5701,"lang":"ja","contributors_enabled":false,"is_translator":false,"is_translation_enabled":false,"profile_background_color":"C0DEED","profile_background_image_url":"http:\/\/abs.twimg.com\/images\/themes\/theme1\/bg.png","profile_background_image_url_https":"https:\/\/abs.twimg.com\/images\/themes\/theme1\/bg.png","profile_background_tile":false,"profile_image_url":"http:\/\/pbs.twimg.com\/profile_images\/641012457910091776\/SK4aML6w_normal.jpg","profile_image_url_https":"https:\/\/pbs.twimg.com\/profile_images\/641012457910091776\/SK4aML6w_normal.jpg","profile_banner_url":"https:\/\/pbs.twimg.com\/profile_banners\/3486272594\/1441664533","profile_link_color":"0084B4","profile_sidebar_border_color":"C0DEED","profile_sidebar_fill_color":"DDEEF6","profile_text_color":"333333","profile_use_background_image":true,"has_extended_profile":false,"default_profile":true,"default_profile_image":false,"following":false,"follow_request_sent":false,"notifications":false},"geo":null,"coordinates":null,"place":null,"contributors":null,"is_quote_status":false,"retweet_count":3,"favorite_count":0,"favorited":false,"retweeted":false,"possibly_sensitive":false,"lang":"ko"},{"created_at":"Thu Sep 08 03:42:38 +0000 2016","id":773728225805541376,"id_str":"773728225805541376","text":"\uc598\ub124 \ubb34\ucc99 \uae38\uac8c \uac08\uac70 \uac19\ub2e4. #Wawrinka vs #DelPotro #USOpen","truncated":false,"entities":{"hashtags":[{"text":"Wawrinka","indices":[16,25]},{"text":"DelPotro","indices":[29,38]},{"text":"USOpen","indices":[39,46]}],"symbols":[],"user_mentions":[],"urls":[]},"metadata":{"result_type":"recent","iso_language_code":"ko"},"source":"\u003ca href=\"http:\/\/twitter.com\" rel=\"nofollow\"\u003eTwitter Web Client\u003c\/a\u003e","in_reply_to_status_id":null,"in_reply_to_status_id_str":null,"in_reply_to_user_id":null,"in_reply_to_user_id_str":null,"in_reply_to_screen_name":null,"user":{"id":32279551,"id_str":"32279551","name":"Sean","screen_name":"supereader","location":"","description":"\ud754\ud55c \ud2b8\uc789\uc5ec","url":null,"entities":{"description":{"urls":[]}},"protected":false,"followers_count":102,"friends_count":79,"listed_count":0,"created_at":"Fri Apr 17 03:08:18 +0000 2009","favourites_count":397,"utc_offset":32400,"time_zone":"Seoul","geo_enabled":false,"verified":false,"statuses_count":111320,"lang":"en","contributors_enabled":false,"is_translator":false,"is_translation_enabled":false,"profile_background_color":"131516","profile_background_image_url":"http:\/\/abs.twimg.com\/images\/themes\/theme14\/bg.gif","profile_background_image_url_https":"https:\/\/abs.twimg.com\/images\/themes\/theme14\/bg.gif","profile_background_tile":true,"profile_image_url":"http:\/\/pbs.twimg.com\/profile_images\/776250557216370688\/J1UYvtye_normal.jpg","profile_image_url_https":"https:\/\/pbs.twimg.com\/profile_images\/776250557216370688\/J1UYvtye_normal.jpg","profile_banner_url":"https:\/\/pbs.twimg.com\/profile_banners\/32279551\/1472835473","profile_link_color":"009999","profile_sidebar_border_color":"EEEEEE","profile_sidebar_fill_color":"EFEFEF","profile_text_color":"333333","profile_use_background_image":true,"has_extended_profile":false,"default_profile":false,"default_profile_image":false,"following":false,"follow_request_sent":false,"notifications":false},"geo":null,"coordinates":null,"place":null,"contributors":null,"is_quote_status":false,"retweet_count":0,"favorite_count":0,"favorited":false,"retweeted":false,"lang":"ko"},{"created_at":"Thu Sep 08 03:06:34 +0000 2016","id":773719146496270336,"id_str":"773719146496270336","text":"1\uc138\ud2b8 \uac00\uc838\uc634 \ud6c4\uc6b0.. \ud798\ub4e4\uad6c\ub098 #StanWawrinka #USOpen","truncated":false,"entities":{"hashtags":[{"text":"StanWawrinka","indices":[18,31]},{"text":"USOpen","indices":[32,39]}],"symbols":[],"user_mentions":[],"urls":[]},"metadata":{"result_type":"recent","iso_language_code":"ko"},"source":"\u003ca href=\"http:\/\/twitter.com\/download\/iphone\" rel=\"nofollow\"\u003eTwitter for iPhone\u003c\/a\u003e","in_reply_to_status_id":null,"in_reply_to_status_id_str":null,"in_reply_to_user_id":null,"in_reply_to_user_id_str":null,"in_reply_to_screen_name":null,"user":{"id":32279551,"id_str":"32279551","name":"Sean","screen_name":"supereader","location":"","description":"\ud754\ud55c \ud2b8\uc789\uc5ec","url":null,"entities":{"description":{"urls":[]}},"protected":false,"followers_count":102,"friends_count":79,"listed_count":0,"created_at":"Fri Apr 17 03:08:18 +0000 2009","favourites_count":397,"utc_offset":32400,"time_zone":"Seoul","geo_enabled":false,"verified":false,"statuses_count":111320,"lang":"en","contributors_enabled":false,"is_translator":false,"is_translation_enabled":false,"profile_background_color":"131516","profile_background_image_url":"http:\/\/abs.twimg.com\/images\/themes\/theme14\/bg.gif","profile_background_image_url_https":"https:\/\/abs.twimg.com\/images\/themes\/theme14\/bg.gif","profile_background_tile":true,"profile_image_url":"http:\/\/pbs.twimg.com\/profile_images\/776250557216370688\/J1UYvtye_normal.jpg","profile_image_url_https":"https:\/\/pbs.twimg.com\/profile_images\/776250557216370688\/J1UYvtye_normal.jpg","profile_banner_url":"https:\/\/pbs.twimg.com\/profile_banners\/32279551\/1472835473","profile_link_color":"009999","profile_sidebar_border_color":"EEEEEE","profile_sidebar_fill_color":"EFEFEF","profile_text_color":"333333","profile_use_background_image":true,"has_extended_profile":false,"default_profile":false,"default_profile_image":false,"following":false,"follow_request_sent":false,"notifications":false},"geo":null,"coordinates":null,"place":null,"contributors":null,"is_quote_status":false,"retweet_count":0,"favorite_count":0,"favorited":false,"retweeted":false,"lang":"ko"},{"created_at":"Thu Sep 08 03:01:14 +0000 2016","id":773717806525198336,"id_str":"773717806525198336","text":"\uccab\uc138\ud2b8 \ud0c0\uc774 #Wawrinka #USOpen","truncated":false,"entities":{"hashtags":[{"text":"Wawrinka","indices":[7,16]},{"text":"USOpen","indices":[17,24]}],"symbols":[],"user_mentions":[],"urls":[]},"metadata":{"result_type":"recent","iso_language_code":"ko"},"source":"\u003ca href=\"http:\/\/twitter.com\/download\/iphone\" rel=\"nofollow\"\u003eTwitter for iPhone\u003c\/a\u003e","in_reply_to_status_id":null,"in_reply_to_status_id_str":null,"in_reply_to_user_id":null,"in_reply_to_user_id_str":null,"in_reply_to_screen_name":null,"user":{"id":32279551,"id_str":"32279551","name":"Sean","screen_name":"supereader","location":"","description":"\ud754\ud55c \ud2b8\uc789\uc5ec","url":null,"entities":{"description":{"urls":[]}},"protected":false,"followers_count":102,"friends_count":79,"listed_count":0,"created_at":"Fri Apr 17 03:08:18 +0000 2009","favourites_count":397,"utc_offset":32400,"time_zone":"Seoul","geo_enabled":false,"verified":false,"statuses_count":111320,"lang":"en","contributors_enabled":false,"is_translator":false,"is_translation_enabled":false,"profile_background_color":"131516","profile_background_image_url":"http:\/\/abs.twimg.com\/images\/themes\/theme14\/bg.gif","profile_background_image_url_https":"https:\/\/abs.twimg.com\/images\/themes\/theme14\/bg.gif","profile_background_tile":true,"profile_image_url":"http:\/\/pbs.twimg.com\/profile_images\/776250557216370688\/J1UYvtye_normal.jpg","profile_image_url_https":"https:\/\/pbs.twimg.com\/profile_images\/776250557216370688\/J1UYvtye_normal.jpg","profile_banner_url":"https:\/\/pbs.twimg.com\/profile_banners\/32279551\/1472835473","profile_link_color":"009999","profile_sidebar_border_color":"EEEEEE","profile_sidebar_fill_color":"EFEFEF","profile_text_color":"333333","profile_use_background_image":true,"has_extended_profile":false,"default_profile":false,"default_profile_image":false,"following":false,"follow_request_sent":false,"notifications":false},"geo":null,"coordinates":null,"place":null,"contributors":null,"is_quote_status":false,"retweet_count":0,"favorite_count":0,"favorited":false,"retweeted":false,"lang":"ko"}],"search_metadata":{"completed_in":0.234,"max_id":777249995648999424,"max_id_str":"777249995648999424","query":"%23usopen+OR+%23trump+OR+%23ISIS","refresh_url":"?since_id=777249995648999424&q=%23usopen%20OR%20%23trump%20OR%20%23ISIS&lang=ko&include_entities=1","count":100,"since_id":0,"since_id_str":"0"}},